{
  "admin_labels": [],
  "amendments": [
    {
      "approved_by": null,
      "exclude": [],
      "include": [],
      "reason": "extract_base + resolve_base_ref + wire into main() landed; tests added; no scope change vs original include set"
    }
  ],
  "branch": "fix/issue-1382/wrapper-base-detection",
  "changed_test_paths": [
    "tests/scripts/test_scistudio_pr_create.py"
  ],
  "check_results": [
    {
      "command_or_tool": "ruff check .",
      "exit_code": 0,
      "name": "ruff",
      "output_path": "All checks passed!",
      "status": "pass",
      "summary": {},
      "timestamp": null
    },
    {
      "command_or_tool": "ruff format --check .",
      "exit_code": 0,
      "name": "format",
      "output_path": "650 files already formatted",
      "status": "pass",
      "summary": {},
      "timestamp": null
    },
    {
      "command_or_tool": "pytest tests/scripts/test_scistudio_pr_create.py --no-cov",
      "exit_code": 0,
      "name": "pytest",
      "output_path": "37 passed in 0.28s",
      "status": "pass",
      "summary": {},
      "timestamp": null
    }
  ],
  "commit": {
    "gate_record_path": ".workflow/records/1382-wrapper-base-detection.json",
    "shas": [
      "f295726937b4c899c4a67e5f7663663513882454"
    ],
    "trailers": {}
  },
  "docs_landing": {
    "adr": {
      "not_applicable": true,
      "rationale": "no-architecture-change"
    },
    "changelog": {
      "paths": [
        "CHANGELOG.md"
      ]
    },
    "checklist": {
      "not_applicable": true,
      "rationale": "standalone-fix-not-part-of-coordinated-dispatch"
    },
    "docs": {},
    "spec": {
      "not_applicable": true,
      "rationale": "no-public-API-change"
    }
  },
  "full_audit": {
    "blocks_merge": false,
    "command": "python -m scistudio.qa.audit.full_audit --repo-root . --format json --output docs/audit/full-audit-latest.json",
    "exit_code": 0,
    "known_debt": [],
    "output_path": "docs/audit/full-audit-latest.json",
    "status": "pass",
    "summary": {},
    "unclassified_failures": []
  },
  "governance_touch": false,
  "issues": [
    {
      "close_in_pr": true,
      "followup_rationale": null,
      "number": 1382,
      "url": null
    }
  ],
  "owner_directive": "Fix scripts/scistudio_pr_create.py to parse --base from argv and pass resolved ref to pre-flight gate_record ci. Removes need for SCISTUDIO_SKIP_PREFLIGHT=1 on umbrella sub-PRs.",
  "planned_files": [
    "scripts/scistudio_pr_create.py",
    "tests/scripts/test_scistudio_pr_create.py",
    "CHANGELOG.md"
  ],
  "pull_request": {
    "body_closes_issues": [
      1382
    ],
    "number": null,
    "url": "https://github.com/zjzcpj/SciStudio/pull/1385"
  },
  "record_path": ".workflow/records/1382-wrapper-base-detection.json",
  "required_checks": [
    "ruff",
    "format",
    "pytest",
    "full_audit",
    "sentrux"
  ],
  "schema_version": "1",
  "scope": {
    "exclude": [],
    "include": [
      "scripts/scistudio_pr_create.py",
      "tests/scripts/test_scistudio_pr_create.py",
      "CHANGELOG.md",
      ".workflow/records/1382-wrapper-base-detection.json"
    ]
  },
  "sentrux": {
    "command_or_tool": "sentrux check",
    "mode": "free-tier",
    "name": "sentrux.free_tier",
    "output_path": "Sentrux does not apply per ADR-042 Addendum 1: changed files are scripts/scistudio_pr_create.py (NOT in IMPLEMENTATION_PATTERNS), tests/scripts/, and CHANGELOG.md. _sentrux_applies returns False for all. Sentrux CLI unavailable locally; CI runs the canonical check on the PR.",
    "pro_required": false,
    "quality_signal": null,
    "rules_checked": null,
    "status": "skipped",
    "summary": {},
    "thresholds": {},
    "total_rules_defined": null
  },
  "stages": [
    {
      "completed_at": null,
      "stage": "scope_and_issue",
      "status": "done",
      "summary": null
    },
    {
      "completed_at": null,
      "stage": "plan",
      "status": "done",
      "summary": null
    },
    {
      "completed_at": null,
      "stage": "implement",
      "status": "done",
      "summary": null
    },
    {
      "completed_at": null,
      "stage": "update_docs",
      "status": "done",
      "summary": null
    },
    {
      "completed_at": null,
      "stage": "test_and_checks",
      "status": "done",
      "summary": null
    },
    {
      "completed_at": null,
      "stage": "commit_and_submit_pr",
      "status": "done",
      "summary": null
    }
  ],
  "task_id": "1382-wrapper-base-detection",
  "task_kind": "bugfix"
}
