{
  "admin_labels": [],
  "amendments": [
    {
      "approved_by": null,
      "exclude": [],
      "include": [
        ".workflow/records/1465-audit-1465-phase3.json"
      ],
      "reason": "include audit gate-record file in scope per ADR-042"
    },
    {
      "approved_by": null,
      "exclude": [],
      "include": [
        ".workflow/audit-pr-body.md"
      ],
      "reason": "include audit PR body file in scope per ADR-042"
    }
  ],
  "branch": "audit/issue-1465/phase3-review",
  "changed_test_paths": [],
  "check_results": [],
  "commit": {
    "gate_record_path": ".workflow/records/1465-audit-1465-phase3.json",
    "shas": [
      "2509fe3c6ff490ee3af07255c1b146ed1b61b3fc"
    ],
    "trailers": {}
  },
  "docs_landing": {
    "changelog": {},
    "checklist": {},
    "docs": {
      "paths": [
        "audit_report=docs/audit/2026-05-22-umbrella-1465-phase3-with-context.md"
      ]
    }
  },
  "full_audit": {
    "blocks_merge": false,
    "command": "python -m scistudio.qa.audit.full_audit (integrated D1+D2+D3' state)",
    "exit_code": 0,
    "known_debt": [],
    "output_path": "docs/audit/full-audit-latest.json",
    "status": "pass",
    "summary": {},
    "unclassified_failures": []
  },
  "governance_touch": true,
  "issues": [
    {
      "close_in_pr": false,
      "followup_rationale": "Issue #1465 is the Phase 3 tracker; it stays open until the umbrella PR #1475 merges to main, per umbrella merge protocol. This audit PR lands the report only; tracking issue is resolved by the umbrella merge, not by this audit landing.",
      "number": 1465,
      "url": null
    }
  ],
  "owner_directive": "Phase 3 Bucket D independent audit (with-context) per dispatch 2026-05-22.",
  "planned_files": [
    "docs/audit/2026-05-22-umbrella-1465-phase3-with-context.md"
  ],
  "pull_request": {
    "body_closes_issues": [],
    "number": null,
    "url": "https://github.com/zjzcpj/SciStudio/pull/1479"
  },
  "record_path": ".workflow/records/1465-audit-1465-phase3.json",
  "required_checks": [],
  "schema_version": "1",
  "scope": {
    "exclude": [],
    "include": [
      "docs/audit/2026-05-22-umbrella-1465-phase3-with-context.md"
    ]
  },
  "sentrux": {
    "command_or_tool": "mcp__plugin_sentrux_sentrux__scan + check_rules + health (integrated D1+D2+D3' state)",
    "mode": "free-tier",
    "name": "sentrux.free_tier",
    "output_path": null,
    "pro_required": false,
    "quality_signal": 4178.0,
    "rules_checked": 3,
    "status": "pass",
    "summary": {},
    "thresholds": {},
    "total_rules_defined": 15
  },
  "stages": [
    {
      "completed_at": null,
      "stage": "scope_and_issue",
      "status": "done",
      "summary": null
    },
    {
      "completed_at": null,
      "stage": "plan",
      "status": "done",
      "summary": null
    },
    {
      "completed_at": null,
      "stage": "implement",
      "status": "done",
      "summary": null
    },
    {
      "completed_at": null,
      "stage": "update_docs",
      "status": "done",
      "summary": null
    },
    {
      "completed_at": null,
      "stage": "test_and_checks",
      "status": "done",
      "summary": null
    },
    {
      "completed_at": null,
      "stage": "commit_and_submit_pr",
      "status": "done",
      "summary": null
    }
  ],
  "task_id": "1465-audit-1465-phase3",
  "task_kind": "docs"
}
