{
  "branch": "fix/git-env-leak-and-gate-hooks-1609",
  "check_events": [
    {
      "at": "2026-06-12T09:43:26.455326Z",
      "command": "ruff format --check .",
      "covered_surface": "python",
      "exit_code": 0,
      "input_fingerprint": "sha256:e3b0c44298fc1c149afbf4c8996fb92427ae41e4649b934ca495991b7852b855",
      "name": "format_check",
      "parity_detail": null,
      "parity_gap": false,
      "pr_only": false,
      "raw_log_ref": ".workflow/local/logs/format_check.log",
      "status": "pass",
      "summary": "clean",
      "tool_versions": {
        "ruff": "0.15.15"
      }
    },
    {
      "at": "2026-06-12T09:43:36.241361Z",
      "command": "python -m scistudio.qa.audit.full_audit --repo-root . --format json --output .audit/full-audit.json",
      "covered_surface": "governance",
      "exit_code": 0,
      "input_fingerprint": "sha256:e3b0c44298fc1c149afbf4c8996fb92427ae41e4649b934ca495991b7852b855",
      "name": "full_audit",
      "parity_detail": null,
      "parity_gap": false,
      "pr_only": false,
      "raw_log_ref": ".workflow/local/logs/full_audit.log",
      "status": "pass",
      "summary": "clean",
      "tool_versions": {}
    },
    {
      "at": "2026-06-12T09:43:36.321178Z",
      "command": "ruff check .",
      "covered_surface": "python",
      "exit_code": 1,
      "input_fingerprint": "sha256:e3b0c44298fc1c149afbf4c8996fb92427ae41e4649b934ca495991b7852b855",
      "name": "lint_format",
      "parity_detail": null,
      "parity_gap": false,
      "pr_only": false,
      "raw_log_ref": ".workflow/local/logs/lint_format.log",
      "status": "fail",
      "summary": "exit 1",
      "tool_versions": {
        "ruff": "0.15.15"
      }
    },
    {
      "at": "2026-06-12T09:44:59.762211Z",
      "command": "ruff format --check .",
      "covered_surface": "python",
      "exit_code": 0,
      "input_fingerprint": "sha256:e3b0c44298fc1c149afbf4c8996fb92427ae41e4649b934ca495991b7852b855",
      "name": "format_check",
      "parity_detail": null,
      "parity_gap": false,
      "pr_only": false,
      "raw_log_ref": ".workflow/local/logs/format_check.log",
      "status": "pass",
      "summary": "clean",
      "tool_versions": {
        "ruff": "0.15.15"
      }
    },
    {
      "at": "2026-06-12T09:45:07.276138Z",
      "command": "python -m scistudio.qa.audit.full_audit --repo-root . --format json --output .audit/full-audit.json",
      "covered_surface": "governance",
      "exit_code": 0,
      "input_fingerprint": "sha256:e3b0c44298fc1c149afbf4c8996fb92427ae41e4649b934ca495991b7852b855",
      "name": "full_audit",
      "parity_detail": null,
      "parity_gap": false,
      "pr_only": false,
      "raw_log_ref": ".workflow/local/logs/full_audit.log",
      "status": "pass",
      "summary": "clean",
      "tool_versions": {}
    },
    {
      "at": "2026-06-12T09:45:07.311202Z",
      "command": "ruff check .",
      "covered_surface": "python",
      "exit_code": 0,
      "input_fingerprint": "sha256:e3b0c44298fc1c149afbf4c8996fb92427ae41e4649b934ca495991b7852b855",
      "name": "lint_format",
      "parity_detail": null,
      "parity_gap": false,
      "pr_only": false,
      "raw_log_ref": ".workflow/local/logs/lint_format.log",
      "status": "pass",
      "summary": "clean",
      "tool_versions": {
        "ruff": "0.15.15"
      }
    },
    {
      "at": "2026-06-12T09:47:52.734239Z",
      "command": "ruff format --check .",
      "covered_surface": "python",
      "exit_code": 0,
      "input_fingerprint": "sha256:e3b0c44298fc1c149afbf4c8996fb92427ae41e4649b934ca495991b7852b855",
      "name": "format_check",
      "parity_detail": null,
      "parity_gap": false,
      "pr_only": false,
      "raw_log_ref": ".workflow/local/logs/format_check.log",
      "status": "pass",
      "summary": "clean",
      "tool_versions": {
        "ruff": "0.15.15"
      }
    },
    {
      "at": "2026-06-12T09:48:00.727709Z",
      "command": "python -m scistudio.qa.audit.full_audit --repo-root . --format json --output .audit/full-audit.json",
      "covered_surface": "governance",
      "exit_code": 0,
      "input_fingerprint": "sha256:e3b0c44298fc1c149afbf4c8996fb92427ae41e4649b934ca495991b7852b855",
      "name": "full_audit",
      "parity_detail": null,
      "parity_gap": false,
      "pr_only": false,
      "raw_log_ref": ".workflow/local/logs/full_audit.log",
      "status": "pass",
      "summary": "clean",
      "tool_versions": {}
    },
    {
      "at": "2026-06-12T09:48:00.763282Z",
      "command": "ruff check .",
      "covered_surface": "python",
      "exit_code": 0,
      "input_fingerprint": "sha256:e3b0c44298fc1c149afbf4c8996fb92427ae41e4649b934ca495991b7852b855",
      "name": "lint_format",
      "parity_detail": null,
      "parity_gap": false,
      "pr_only": false,
      "raw_log_ref": ".workflow/local/logs/lint_format.log",
      "status": "pass",
      "summary": "clean",
      "tool_versions": {
        "ruff": "0.15.15"
      }
    },
    {
      "at": "2026-06-12T09:51:57.640695Z",
      "command": "ruff format --check .",
      "covered_surface": "python",
      "exit_code": 0,
      "input_fingerprint": "sha256:e3b0c44298fc1c149afbf4c8996fb92427ae41e4649b934ca495991b7852b855",
      "name": "format_check",
      "parity_detail": null,
      "parity_gap": false,
      "pr_only": false,
      "raw_log_ref": ".workflow/local/logs/format_check.log",
      "status": "pass",
      "summary": "clean",
      "tool_versions": {
        "ruff": "0.15.15"
      }
    },
    {
      "at": "2026-06-12T09:52:05.764867Z",
      "command": "python -m scistudio.qa.audit.full_audit --repo-root . --format json --output .audit/full-audit.json",
      "covered_surface": "governance",
      "exit_code": 0,
      "input_fingerprint": "sha256:e3b0c44298fc1c149afbf4c8996fb92427ae41e4649b934ca495991b7852b855",
      "name": "full_audit",
      "parity_detail": null,
      "parity_gap": false,
      "pr_only": false,
      "raw_log_ref": ".workflow/local/logs/full_audit.log",
      "status": "pass",
      "summary": "clean",
      "tool_versions": {}
    },
    {
      "at": "2026-06-12T09:52:05.799910Z",
      "command": "ruff check .",
      "covered_surface": "python",
      "exit_code": 0,
      "input_fingerprint": "sha256:e3b0c44298fc1c149afbf4c8996fb92427ae41e4649b934ca495991b7852b855",
      "name": "lint_format",
      "parity_detail": null,
      "parity_gap": false,
      "pr_only": false,
      "raw_log_ref": ".workflow/local/logs/lint_format.log",
      "status": "pass",
      "summary": "clean",
      "tool_versions": {
        "ruff": "0.15.15"
      }
    },
    {
      "at": "2026-06-12T09:59:53.084950Z",
      "command": "pytest tests/architecture/ -v --no-cov",
      "covered_surface": "architecture",
      "exit_code": 0,
      "input_fingerprint": "sha256:e6d12cba51239e2a1902dbcf22675c0f940678d39230b9d22bf2474fb822d1bb",
      "name": "architecture_tests",
      "parity_detail": null,
      "parity_gap": false,
      "pr_only": false,
      "raw_log_ref": ".workflow/local/logs/architecture_tests.log",
      "status": "pass",
      "summary": "clean",
      "tool_versions": {}
    },
    {
      "at": "2026-06-12T09:59:53.121322Z",
      "command": "ruff format --check .",
      "covered_surface": "python",
      "exit_code": 0,
      "input_fingerprint": "sha256:e6d12cba51239e2a1902dbcf22675c0f940678d39230b9d22bf2474fb822d1bb",
      "name": "format_check",
      "parity_detail": null,
      "parity_gap": false,
      "pr_only": false,
      "raw_log_ref": ".workflow/local/logs/format_check.log",
      "status": "pass",
      "summary": "clean",
      "tool_versions": {
        "ruff": "0.15.15"
      }
    },
    {
      "at": "2026-06-12T10:00:01.077681Z",
      "command": "python -m scistudio.qa.audit.full_audit --repo-root . --format json --output .audit/full-audit.json",
      "covered_surface": "governance",
      "exit_code": 0,
      "input_fingerprint": "sha256:e6d12cba51239e2a1902dbcf22675c0f940678d39230b9d22bf2474fb822d1bb",
      "name": "full_audit",
      "parity_detail": null,
      "parity_gap": false,
      "pr_only": false,
      "raw_log_ref": ".workflow/local/logs/full_audit.log",
      "status": "pass",
      "summary": "clean",
      "tool_versions": {}
    },
    {
      "at": "2026-06-12T10:00:01.689847Z",
      "command": "lint-imports",
      "covered_surface": "python",
      "exit_code": 0,
      "input_fingerprint": "sha256:e6d12cba51239e2a1902dbcf22675c0f940678d39230b9d22bf2474fb822d1bb",
      "name": "import_contracts",
      "parity_detail": null,
      "parity_gap": false,
      "pr_only": false,
      "raw_log_ref": ".workflow/local/logs/import_contracts.log",
      "status": "pass",
      "summary": "clean",
      "tool_versions": {}
    },
    {
      "at": "2026-06-12T10:00:01.721492Z",
      "command": "ruff check .",
      "covered_surface": "python",
      "exit_code": 0,
      "input_fingerprint": "sha256:e6d12cba51239e2a1902dbcf22675c0f940678d39230b9d22bf2474fb822d1bb",
      "name": "lint_format",
      "parity_detail": null,
      "parity_gap": false,
      "pr_only": false,
      "raw_log_ref": ".workflow/local/logs/lint_format.log",
      "status": "pass",
      "summary": "clean",
      "tool_versions": {
        "ruff": "0.15.15"
      }
    },
    {
      "at": "2026-06-12T10:02:16.711478Z",
      "command": "pytest -n auto --timeout=60 --timeout-method=thread",
      "covered_surface": "python",
      "exit_code": 0,
      "input_fingerprint": "sha256:e6d12cba51239e2a1902dbcf22675c0f940678d39230b9d22bf2474fb822d1bb",
      "name": "python_tests",
      "parity_detail": null,
      "parity_gap": false,
      "pr_only": false,
      "raw_log_ref": ".workflow/local/logs/python_tests.log",
      "status": "pass",
      "summary": "clean",
      "tool_versions": {}
    },
    {
      "at": "2026-06-12T10:03:06.646219Z",
      "command": "python scripts/semantic_dup_scan.py --check docs/audit/baselines/semantic-dup-baseline.json",
      "covered_surface": "python",
      "exit_code": 0,
      "input_fingerprint": "sha256:e6d12cba51239e2a1902dbcf22675c0f940678d39230b9d22bf2474fb822d1bb",
      "name": "semantic_dup",
      "parity_detail": null,
      "parity_gap": false,
      "pr_only": false,
      "raw_log_ref": ".workflow/local/logs/semantic_dup.log",
      "status": "pass",
      "summary": "clean",
      "tool_versions": {}
    },
    {
      "at": "2026-06-12T10:03:14.981884Z",
      "command": "mypy src/scistudio/ --ignore-missing-imports",
      "covered_surface": "python",
      "exit_code": 0,
      "input_fingerprint": "sha256:e6d12cba51239e2a1902dbcf22675c0f940678d39230b9d22bf2474fb822d1bb",
      "name": "type_check",
      "parity_detail": null,
      "parity_gap": false,
      "pr_only": false,
      "raw_log_ref": ".workflow/local/logs/type_check.log",
      "status": "pass",
      "summary": "clean",
      "tool_versions": {
        "mypy": "2.1.0"
      }
    },
    {
      "at": "2026-06-12T10:12:40.746373Z",
      "command": "pytest tests/architecture/ -v --no-cov",
      "covered_surface": "architecture",
      "exit_code": 0,
      "input_fingerprint": "sha256:e6d12cba51239e2a1902dbcf22675c0f940678d39230b9d22bf2474fb822d1bb",
      "name": "architecture_tests",
      "parity_detail": null,
      "parity_gap": false,
      "pr_only": false,
      "raw_log_ref": ".workflow/local/logs/architecture_tests.log",
      "status": "pass",
      "summary": "clean",
      "tool_versions": {}
    },
    {
      "at": "2026-06-12T10:12:40.784862Z",
      "command": "ruff format --check .",
      "covered_surface": "python",
      "exit_code": 0,
      "input_fingerprint": "sha256:e6d12cba51239e2a1902dbcf22675c0f940678d39230b9d22bf2474fb822d1bb",
      "name": "format_check",
      "parity_detail": null,
      "parity_gap": false,
      "pr_only": false,
      "raw_log_ref": ".workflow/local/logs/format_check.log",
      "status": "pass",
      "summary": "clean",
      "tool_versions": {
        "ruff": "0.15.15"
      }
    },
    {
      "at": "2026-06-12T10:12:48.873990Z",
      "command": "python -m scistudio.qa.audit.full_audit --repo-root . --format json --output .audit/full-audit.json",
      "covered_surface": "governance",
      "exit_code": 0,
      "input_fingerprint": "sha256:e6d12cba51239e2a1902dbcf22675c0f940678d39230b9d22bf2474fb822d1bb",
      "name": "full_audit",
      "parity_detail": null,
      "parity_gap": false,
      "pr_only": false,
      "raw_log_ref": ".workflow/local/logs/full_audit.log",
      "status": "pass",
      "summary": "clean",
      "tool_versions": {}
    },
    {
      "at": "2026-06-12T10:12:49.088077Z",
      "command": "lint-imports",
      "covered_surface": "python",
      "exit_code": 0,
      "input_fingerprint": "sha256:e6d12cba51239e2a1902dbcf22675c0f940678d39230b9d22bf2474fb822d1bb",
      "name": "import_contracts",
      "parity_detail": null,
      "parity_gap": false,
      "pr_only": false,
      "raw_log_ref": ".workflow/local/logs/import_contracts.log",
      "status": "pass",
      "summary": "clean",
      "tool_versions": {}
    },
    {
      "at": "2026-06-12T10:12:49.123234Z",
      "command": "ruff check .",
      "covered_surface": "python",
      "exit_code": 0,
      "input_fingerprint": "sha256:e6d12cba51239e2a1902dbcf22675c0f940678d39230b9d22bf2474fb822d1bb",
      "name": "lint_format",
      "parity_detail": null,
      "parity_gap": false,
      "pr_only": false,
      "raw_log_ref": ".workflow/local/logs/lint_format.log",
      "status": "pass",
      "summary": "clean",
      "tool_versions": {
        "ruff": "0.15.15"
      }
    },
    {
      "at": "2026-06-12T10:14:55.959189Z",
      "command": "pytest -n auto --timeout=60 --timeout-method=thread",
      "covered_surface": "python",
      "exit_code": 0,
      "input_fingerprint": "sha256:e6d12cba51239e2a1902dbcf22675c0f940678d39230b9d22bf2474fb822d1bb",
      "name": "python_tests",
      "parity_detail": null,
      "parity_gap": false,
      "pr_only": false,
      "raw_log_ref": ".workflow/local/logs/python_tests.log",
      "status": "pass",
      "summary": "clean",
      "tool_versions": {}
    },
    {
      "at": "2026-06-12T10:15:44.222890Z",
      "command": "python scripts/semantic_dup_scan.py --check docs/audit/baselines/semantic-dup-baseline.json",
      "covered_surface": "python",
      "exit_code": 0,
      "input_fingerprint": "sha256:e6d12cba51239e2a1902dbcf22675c0f940678d39230b9d22bf2474fb822d1bb",
      "name": "semantic_dup",
      "parity_detail": null,
      "parity_gap": false,
      "pr_only": false,
      "raw_log_ref": ".workflow/local/logs/semantic_dup.log",
      "status": "pass",
      "summary": "clean",
      "tool_versions": {}
    },
    {
      "at": "2026-06-12T10:15:47.039081Z",
      "command": "mypy src/scistudio/ --ignore-missing-imports",
      "covered_surface": "python",
      "exit_code": 0,
      "input_fingerprint": "sha256:e6d12cba51239e2a1902dbcf22675c0f940678d39230b9d22bf2474fb822d1bb",
      "name": "type_check",
      "parity_detail": null,
      "parity_gap": false,
      "pr_only": false,
      "raw_log_ref": ".workflow/local/logs/type_check.log",
      "status": "pass",
      "summary": "clean",
      "tool_versions": {
        "mypy": "2.1.0"
      }
    },
    {
      "at": "2026-06-12T10:16:42.795074Z",
      "command": "pytest tests/architecture/ -v --no-cov",
      "covered_surface": "architecture",
      "exit_code": 0,
      "input_fingerprint": "sha256:e6d12cba51239e2a1902dbcf22675c0f940678d39230b9d22bf2474fb822d1bb",
      "name": "architecture_tests",
      "parity_detail": null,
      "parity_gap": false,
      "pr_only": false,
      "raw_log_ref": ".workflow/local/logs/architecture_tests.log",
      "status": "pass",
      "summary": "clean",
      "tool_versions": {}
    },
    {
      "at": "2026-06-12T10:16:42.830784Z",
      "command": "ruff format --check .",
      "covered_surface": "python",
      "exit_code": 0,
      "input_fingerprint": "sha256:e6d12cba51239e2a1902dbcf22675c0f940678d39230b9d22bf2474fb822d1bb",
      "name": "format_check",
      "parity_detail": null,
      "parity_gap": false,
      "pr_only": false,
      "raw_log_ref": ".workflow/local/logs/format_check.log",
      "status": "pass",
      "summary": "clean",
      "tool_versions": {
        "ruff": "0.15.15"
      }
    },
    {
      "at": "2026-06-12T10:16:51.043816Z",
      "command": "python -m scistudio.qa.audit.full_audit --repo-root . --format json --output .audit/full-audit.json",
      "covered_surface": "governance",
      "exit_code": 0,
      "input_fingerprint": "sha256:e6d12cba51239e2a1902dbcf22675c0f940678d39230b9d22bf2474fb822d1bb",
      "name": "full_audit",
      "parity_detail": null,
      "parity_gap": false,
      "pr_only": false,
      "raw_log_ref": ".workflow/local/logs/full_audit.log",
      "status": "pass",
      "summary": "clean",
      "tool_versions": {}
    },
    {
      "at": "2026-06-12T10:16:51.251805Z",
      "command": "lint-imports",
      "covered_surface": "python",
      "exit_code": 0,
      "input_fingerprint": "sha256:e6d12cba51239e2a1902dbcf22675c0f940678d39230b9d22bf2474fb822d1bb",
      "name": "import_contracts",
      "parity_detail": null,
      "parity_gap": false,
      "pr_only": false,
      "raw_log_ref": ".workflow/local/logs/import_contracts.log",
      "status": "pass",
      "summary": "clean",
      "tool_versions": {}
    },
    {
      "at": "2026-06-12T10:16:51.287928Z",
      "command": "ruff check .",
      "covered_surface": "python",
      "exit_code": 0,
      "input_fingerprint": "sha256:e6d12cba51239e2a1902dbcf22675c0f940678d39230b9d22bf2474fb822d1bb",
      "name": "lint_format",
      "parity_detail": null,
      "parity_gap": false,
      "pr_only": false,
      "raw_log_ref": ".workflow/local/logs/lint_format.log",
      "status": "pass",
      "summary": "clean",
      "tool_versions": {
        "ruff": "0.15.15"
      }
    },
    {
      "at": "2026-06-12T10:18:55.487978Z",
      "command": "pytest -n auto --timeout=60 --timeout-method=thread",
      "covered_surface": "python",
      "exit_code": 0,
      "input_fingerprint": "sha256:e6d12cba51239e2a1902dbcf22675c0f940678d39230b9d22bf2474fb822d1bb",
      "name": "python_tests",
      "parity_detail": null,
      "parity_gap": false,
      "pr_only": false,
      "raw_log_ref": ".workflow/local/logs/python_tests.log",
      "status": "pass",
      "summary": "clean",
      "tool_versions": {}
    },
    {
      "at": "2026-06-12T10:19:43.112727Z",
      "command": "python scripts/semantic_dup_scan.py --check docs/audit/baselines/semantic-dup-baseline.json",
      "covered_surface": "python",
      "exit_code": 0,
      "input_fingerprint": "sha256:e6d12cba51239e2a1902dbcf22675c0f940678d39230b9d22bf2474fb822d1bb",
      "name": "semantic_dup",
      "parity_detail": null,
      "parity_gap": false,
      "pr_only": false,
      "raw_log_ref": ".workflow/local/logs/semantic_dup.log",
      "status": "pass",
      "summary": "clean",
      "tool_versions": {}
    },
    {
      "at": "2026-06-12T10:19:45.784371Z",
      "command": "mypy src/scistudio/ --ignore-missing-imports",
      "covered_surface": "python",
      "exit_code": 0,
      "input_fingerprint": "sha256:e6d12cba51239e2a1902dbcf22675c0f940678d39230b9d22bf2474fb822d1bb",
      "name": "type_check",
      "parity_detail": null,
      "parity_gap": false,
      "pr_only": false,
      "raw_log_ref": ".workflow/local/logs/type_check.log",
      "status": "pass",
      "summary": "clean",
      "tool_versions": {
        "mypy": "2.1.0"
      }
    },
    {
      "at": "2026-06-12T10:27:09.398265Z",
      "command": "pytest tests/architecture/ -v --no-cov",
      "covered_surface": "architecture",
      "exit_code": 0,
      "input_fingerprint": "sha256:1db8f76b328d1fa075bd703d9dd4debd5b2b08290f2dee272b4a14b13d57b60b",
      "name": "architecture_tests",
      "parity_detail": null,
      "parity_gap": false,
      "pr_only": false,
      "raw_log_ref": ".workflow/local/logs/architecture_tests.log",
      "status": "pass",
      "summary": "clean",
      "tool_versions": {}
    },
    {
      "at": "2026-06-12T10:27:09.436126Z",
      "command": "ruff format --check .",
      "covered_surface": "python",
      "exit_code": 0,
      "input_fingerprint": "sha256:1db8f76b328d1fa075bd703d9dd4debd5b2b08290f2dee272b4a14b13d57b60b",
      "name": "format_check",
      "parity_detail": null,
      "parity_gap": false,
      "pr_only": false,
      "raw_log_ref": ".workflow/local/logs/format_check.log",
      "status": "pass",
      "summary": "clean",
      "tool_versions": {
        "ruff": "0.15.15"
      }
    },
    {
      "at": "2026-06-12T10:27:17.569789Z",
      "command": "python -m scistudio.qa.audit.full_audit --repo-root . --format json --output .audit/full-audit.json",
      "covered_surface": "governance",
      "exit_code": 0,
      "input_fingerprint": "sha256:1db8f76b328d1fa075bd703d9dd4debd5b2b08290f2dee272b4a14b13d57b60b",
      "name": "full_audit",
      "parity_detail": null,
      "parity_gap": false,
      "pr_only": false,
      "raw_log_ref": ".workflow/local/logs/full_audit.log",
      "status": "pass",
      "summary": "clean",
      "tool_versions": {}
    },
    {
      "at": "2026-06-12T10:27:17.784208Z",
      "command": "lint-imports",
      "covered_surface": "python",
      "exit_code": 0,
      "input_fingerprint": "sha256:1db8f76b328d1fa075bd703d9dd4debd5b2b08290f2dee272b4a14b13d57b60b",
      "name": "import_contracts",
      "parity_detail": null,
      "parity_gap": false,
      "pr_only": false,
      "raw_log_ref": ".workflow/local/logs/import_contracts.log",
      "status": "pass",
      "summary": "clean",
      "tool_versions": {}
    },
    {
      "at": "2026-06-12T10:27:17.822235Z",
      "command": "ruff check .",
      "covered_surface": "python",
      "exit_code": 0,
      "input_fingerprint": "sha256:1db8f76b328d1fa075bd703d9dd4debd5b2b08290f2dee272b4a14b13d57b60b",
      "name": "lint_format",
      "parity_detail": null,
      "parity_gap": false,
      "pr_only": false,
      "raw_log_ref": ".workflow/local/logs/lint_format.log",
      "status": "pass",
      "summary": "clean",
      "tool_versions": {
        "ruff": "0.15.15"
      }
    },
    {
      "at": "2026-06-12T10:29:17.992484Z",
      "command": "pytest -n auto --timeout=60 --timeout-method=thread",
      "covered_surface": "python",
      "exit_code": 0,
      "input_fingerprint": "sha256:1db8f76b328d1fa075bd703d9dd4debd5b2b08290f2dee272b4a14b13d57b60b",
      "name": "python_tests",
      "parity_detail": null,
      "parity_gap": false,
      "pr_only": false,
      "raw_log_ref": ".workflow/local/logs/python_tests.log",
      "status": "pass",
      "summary": "clean",
      "tool_versions": {}
    },
    {
      "at": "2026-06-12T10:30:04.234867Z",
      "command": "python scripts/semantic_dup_scan.py --check docs/audit/baselines/semantic-dup-baseline.json",
      "covered_surface": "python",
      "exit_code": 0,
      "input_fingerprint": "sha256:1db8f76b328d1fa075bd703d9dd4debd5b2b08290f2dee272b4a14b13d57b60b",
      "name": "semantic_dup",
      "parity_detail": null,
      "parity_gap": false,
      "pr_only": false,
      "raw_log_ref": ".workflow/local/logs/semantic_dup.log",
      "status": "pass",
      "summary": "clean",
      "tool_versions": {}
    },
    {
      "at": "2026-06-12T10:30:06.963567Z",
      "command": "mypy src/scistudio/ --ignore-missing-imports",
      "covered_surface": "python",
      "exit_code": 0,
      "input_fingerprint": "sha256:1db8f76b328d1fa075bd703d9dd4debd5b2b08290f2dee272b4a14b13d57b60b",
      "name": "type_check",
      "parity_detail": null,
      "parity_gap": false,
      "pr_only": false,
      "raw_log_ref": ".workflow/local/logs/type_check.log",
      "status": "pass",
      "summary": "clean",
      "tool_versions": {
        "mypy": "2.1.0"
      }
    },
    {
      "at": "2026-06-12T10:30:40.170916Z",
      "command": "pytest tests/architecture/ -v --no-cov",
      "covered_surface": "architecture",
      "exit_code": 0,
      "input_fingerprint": "sha256:1db8f76b328d1fa075bd703d9dd4debd5b2b08290f2dee272b4a14b13d57b60b",
      "name": "architecture_tests",
      "parity_detail": null,
      "parity_gap": false,
      "pr_only": false,
      "raw_log_ref": ".workflow/local/logs/architecture_tests.log",
      "status": "pass",
      "summary": "clean",
      "tool_versions": {}
    },
    {
      "at": "2026-06-12T10:30:40.208403Z",
      "command": "ruff format --check .",
      "covered_surface": "python",
      "exit_code": 0,
      "input_fingerprint": "sha256:1db8f76b328d1fa075bd703d9dd4debd5b2b08290f2dee272b4a14b13d57b60b",
      "name": "format_check",
      "parity_detail": null,
      "parity_gap": false,
      "pr_only": false,
      "raw_log_ref": ".workflow/local/logs/format_check.log",
      "status": "pass",
      "summary": "clean",
      "tool_versions": {
        "ruff": "0.15.15"
      }
    },
    {
      "at": "2026-06-12T10:30:48.335402Z",
      "command": "python -m scistudio.qa.audit.full_audit --repo-root . --format json --output .audit/full-audit.json",
      "covered_surface": "governance",
      "exit_code": 0,
      "input_fingerprint": "sha256:1db8f76b328d1fa075bd703d9dd4debd5b2b08290f2dee272b4a14b13d57b60b",
      "name": "full_audit",
      "parity_detail": null,
      "parity_gap": false,
      "pr_only": false,
      "raw_log_ref": ".workflow/local/logs/full_audit.log",
      "status": "pass",
      "summary": "clean",
      "tool_versions": {}
    },
    {
      "at": "2026-06-12T10:30:48.551301Z",
      "command": "lint-imports",
      "covered_surface": "python",
      "exit_code": 0,
      "input_fingerprint": "sha256:1db8f76b328d1fa075bd703d9dd4debd5b2b08290f2dee272b4a14b13d57b60b",
      "name": "import_contracts",
      "parity_detail": null,
      "parity_gap": false,
      "pr_only": false,
      "raw_log_ref": ".workflow/local/logs/import_contracts.log",
      "status": "pass",
      "summary": "clean",
      "tool_versions": {}
    },
    {
      "at": "2026-06-12T10:30:48.585225Z",
      "command": "ruff check .",
      "covered_surface": "python",
      "exit_code": 0,
      "input_fingerprint": "sha256:1db8f76b328d1fa075bd703d9dd4debd5b2b08290f2dee272b4a14b13d57b60b",
      "name": "lint_format",
      "parity_detail": null,
      "parity_gap": false,
      "pr_only": false,
      "raw_log_ref": ".workflow/local/logs/lint_format.log",
      "status": "pass",
      "summary": "clean",
      "tool_versions": {
        "ruff": "0.15.15"
      }
    },
    {
      "at": "2026-06-12T10:32:50.540405Z",
      "command": "pytest -n auto --timeout=60 --timeout-method=thread",
      "covered_surface": "python",
      "exit_code": 0,
      "input_fingerprint": "sha256:1db8f76b328d1fa075bd703d9dd4debd5b2b08290f2dee272b4a14b13d57b60b",
      "name": "python_tests",
      "parity_detail": null,
      "parity_gap": false,
      "pr_only": false,
      "raw_log_ref": ".workflow/local/logs/python_tests.log",
      "status": "pass",
      "summary": "clean",
      "tool_versions": {}
    },
    {
      "at": "2026-06-12T10:33:36.970840Z",
      "command": "python scripts/semantic_dup_scan.py --check docs/audit/baselines/semantic-dup-baseline.json",
      "covered_surface": "python",
      "exit_code": 0,
      "input_fingerprint": "sha256:1db8f76b328d1fa075bd703d9dd4debd5b2b08290f2dee272b4a14b13d57b60b",
      "name": "semantic_dup",
      "parity_detail": null,
      "parity_gap": false,
      "pr_only": false,
      "raw_log_ref": ".workflow/local/logs/semantic_dup.log",
      "status": "pass",
      "summary": "clean",
      "tool_versions": {}
    },
    {
      "at": "2026-06-12T10:33:39.154482Z",
      "command": "mypy src/scistudio/ --ignore-missing-imports",
      "covered_surface": "python",
      "exit_code": 0,
      "input_fingerprint": "sha256:1db8f76b328d1fa075bd703d9dd4debd5b2b08290f2dee272b4a14b13d57b60b",
      "name": "type_check",
      "parity_detail": null,
      "parity_gap": false,
      "pr_only": false,
      "raw_log_ref": ".workflow/local/logs/type_check.log",
      "status": "pass",
      "summary": "clean",
      "tool_versions": {
        "mypy": "2.1.0"
      }
    },
    {
      "at": "2026-06-12T11:35:24.554386Z",
      "command": "pytest tests/architecture/ -v --no-cov",
      "covered_surface": "architecture",
      "exit_code": 0,
      "input_fingerprint": "sha256:5ede1d49fb8dfd78571108ce39ef8fc8ce6d3cd58fe19c86493cffdc1f875f99",
      "name": "architecture_tests",
      "parity_detail": null,
      "parity_gap": false,
      "pr_only": false,
      "raw_log_ref": ".workflow/local/logs/architecture_tests.log",
      "status": "pass",
      "summary": "clean",
      "tool_versions": {}
    },
    {
      "at": "2026-06-12T11:35:24.592644Z",
      "command": "ruff format --check .",
      "covered_surface": "python",
      "exit_code": 0,
      "input_fingerprint": "sha256:5ede1d49fb8dfd78571108ce39ef8fc8ce6d3cd58fe19c86493cffdc1f875f99",
      "name": "format_check",
      "parity_detail": null,
      "parity_gap": false,
      "pr_only": false,
      "raw_log_ref": ".workflow/local/logs/format_check.log",
      "status": "pass",
      "summary": "clean",
      "tool_versions": {
        "ruff": "0.15.15"
      }
    },
    {
      "at": "2026-06-12T11:35:32.634325Z",
      "command": "python -m scistudio.qa.audit.full_audit --repo-root . --format json --output .audit/full-audit.json",
      "covered_surface": "governance",
      "exit_code": 0,
      "input_fingerprint": "sha256:5ede1d49fb8dfd78571108ce39ef8fc8ce6d3cd58fe19c86493cffdc1f875f99",
      "name": "full_audit",
      "parity_detail": null,
      "parity_gap": false,
      "pr_only": false,
      "raw_log_ref": ".workflow/local/logs/full_audit.log",
      "status": "pass",
      "summary": "clean",
      "tool_versions": {}
    },
    {
      "at": "2026-06-12T11:35:32.850072Z",
      "command": "lint-imports",
      "covered_surface": "python",
      "exit_code": 0,
      "input_fingerprint": "sha256:5ede1d49fb8dfd78571108ce39ef8fc8ce6d3cd58fe19c86493cffdc1f875f99",
      "name": "import_contracts",
      "parity_detail": null,
      "parity_gap": false,
      "pr_only": false,
      "raw_log_ref": ".workflow/local/logs/import_contracts.log",
      "status": "pass",
      "summary": "clean",
      "tool_versions": {}
    },
    {
      "at": "2026-06-12T11:35:32.884489Z",
      "command": "ruff check .",
      "covered_surface": "python",
      "exit_code": 0,
      "input_fingerprint": "sha256:5ede1d49fb8dfd78571108ce39ef8fc8ce6d3cd58fe19c86493cffdc1f875f99",
      "name": "lint_format",
      "parity_detail": null,
      "parity_gap": false,
      "pr_only": false,
      "raw_log_ref": ".workflow/local/logs/lint_format.log",
      "status": "pass",
      "summary": "clean",
      "tool_versions": {
        "ruff": "0.15.15"
      }
    },
    {
      "at": "2026-06-12T11:37:35.339545Z",
      "command": "pytest -n auto --timeout=60 --timeout-method=thread",
      "covered_surface": "python",
      "exit_code": 0,
      "input_fingerprint": "sha256:5ede1d49fb8dfd78571108ce39ef8fc8ce6d3cd58fe19c86493cffdc1f875f99",
      "name": "python_tests",
      "parity_detail": null,
      "parity_gap": false,
      "pr_only": false,
      "raw_log_ref": ".workflow/local/logs/python_tests.log",
      "status": "pass",
      "summary": "clean",
      "tool_versions": {}
    },
    {
      "at": "2026-06-12T11:38:23.535704Z",
      "command": "python scripts/semantic_dup_scan.py --check docs/audit/baselines/semantic-dup-baseline.json",
      "covered_surface": "python",
      "exit_code": 0,
      "input_fingerprint": "sha256:5ede1d49fb8dfd78571108ce39ef8fc8ce6d3cd58fe19c86493cffdc1f875f99",
      "name": "semantic_dup",
      "parity_detail": null,
      "parity_gap": false,
      "pr_only": false,
      "raw_log_ref": ".workflow/local/logs/semantic_dup.log",
      "status": "pass",
      "summary": "clean",
      "tool_versions": {}
    },
    {
      "at": "2026-06-12T11:38:24.758262Z",
      "command": "mypy src/scistudio/ --ignore-missing-imports",
      "covered_surface": "python",
      "exit_code": 0,
      "input_fingerprint": "sha256:5ede1d49fb8dfd78571108ce39ef8fc8ce6d3cd58fe19c86493cffdc1f875f99",
      "name": "type_check",
      "parity_detail": null,
      "parity_gap": false,
      "pr_only": false,
      "raw_log_ref": ".workflow/local/logs/type_check.log",
      "status": "pass",
      "summary": "clean",
      "tool_versions": {
        "mypy": "2.1.0"
      }
    },
    {
      "at": "2026-06-12T11:42:02.670531Z",
      "command": "pytest tests/architecture/ -v --no-cov",
      "covered_surface": "architecture",
      "exit_code": 0,
      "input_fingerprint": "sha256:5ede1d49fb8dfd78571108ce39ef8fc8ce6d3cd58fe19c86493cffdc1f875f99",
      "name": "architecture_tests",
      "parity_detail": null,
      "parity_gap": false,
      "pr_only": false,
      "raw_log_ref": ".workflow/local/logs/architecture_tests.log",
      "status": "pass",
      "summary": "clean",
      "tool_versions": {}
    },
    {
      "at": "2026-06-12T11:42:02.706029Z",
      "command": "ruff format --check .",
      "covered_surface": "python",
      "exit_code": 0,
      "input_fingerprint": "sha256:5ede1d49fb8dfd78571108ce39ef8fc8ce6d3cd58fe19c86493cffdc1f875f99",
      "name": "format_check",
      "parity_detail": null,
      "parity_gap": false,
      "pr_only": false,
      "raw_log_ref": ".workflow/local/logs/format_check.log",
      "status": "pass",
      "summary": "clean",
      "tool_versions": {
        "ruff": "0.15.15"
      }
    },
    {
      "at": "2026-06-12T11:42:10.453776Z",
      "command": "python -m scistudio.qa.audit.full_audit --repo-root . --format json --output .audit/full-audit.json",
      "covered_surface": "governance",
      "exit_code": 0,
      "input_fingerprint": "sha256:5ede1d49fb8dfd78571108ce39ef8fc8ce6d3cd58fe19c86493cffdc1f875f99",
      "name": "full_audit",
      "parity_detail": null,
      "parity_gap": false,
      "pr_only": false,
      "raw_log_ref": ".workflow/local/logs/full_audit.log",
      "status": "pass",
      "summary": "clean",
      "tool_versions": {}
    },
    {
      "at": "2026-06-12T11:42:10.670794Z",
      "command": "lint-imports",
      "covered_surface": "python",
      "exit_code": 0,
      "input_fingerprint": "sha256:5ede1d49fb8dfd78571108ce39ef8fc8ce6d3cd58fe19c86493cffdc1f875f99",
      "name": "import_contracts",
      "parity_detail": null,
      "parity_gap": false,
      "pr_only": false,
      "raw_log_ref": ".workflow/local/logs/import_contracts.log",
      "status": "pass",
      "summary": "clean",
      "tool_versions": {}
    },
    {
      "at": "2026-06-12T11:42:10.704158Z",
      "command": "ruff check .",
      "covered_surface": "python",
      "exit_code": 0,
      "input_fingerprint": "sha256:5ede1d49fb8dfd78571108ce39ef8fc8ce6d3cd58fe19c86493cffdc1f875f99",
      "name": "lint_format",
      "parity_detail": null,
      "parity_gap": false,
      "pr_only": false,
      "raw_log_ref": ".workflow/local/logs/lint_format.log",
      "status": "pass",
      "summary": "clean",
      "tool_versions": {
        "ruff": "0.15.15"
      }
    },
    {
      "at": "2026-06-12T11:44:13.816634Z",
      "command": "pytest -n auto --timeout=60 --timeout-method=thread",
      "covered_surface": "python",
      "exit_code": 0,
      "input_fingerprint": "sha256:5ede1d49fb8dfd78571108ce39ef8fc8ce6d3cd58fe19c86493cffdc1f875f99",
      "name": "python_tests",
      "parity_detail": null,
      "parity_gap": false,
      "pr_only": false,
      "raw_log_ref": ".workflow/local/logs/python_tests.log",
      "status": "pass",
      "summary": "clean",
      "tool_versions": {}
    },
    {
      "at": "2026-06-12T11:45:01.130667Z",
      "command": "python scripts/semantic_dup_scan.py --check docs/audit/baselines/semantic-dup-baseline.json",
      "covered_surface": "python",
      "exit_code": 0,
      "input_fingerprint": "sha256:5ede1d49fb8dfd78571108ce39ef8fc8ce6d3cd58fe19c86493cffdc1f875f99",
      "name": "semantic_dup",
      "parity_detail": null,
      "parity_gap": false,
      "pr_only": false,
      "raw_log_ref": ".workflow/local/logs/semantic_dup.log",
      "status": "pass",
      "summary": "clean",
      "tool_versions": {}
    },
    {
      "at": "2026-06-12T11:45:01.763742Z",
      "command": "mypy src/scistudio/ --ignore-missing-imports",
      "covered_surface": "python",
      "exit_code": 0,
      "input_fingerprint": "sha256:5ede1d49fb8dfd78571108ce39ef8fc8ce6d3cd58fe19c86493cffdc1f875f99",
      "name": "type_check",
      "parity_detail": null,
      "parity_gap": false,
      "pr_only": false,
      "raw_log_ref": ".workflow/local/logs/type_check.log",
      "status": "pass",
      "summary": "clean",
      "tool_versions": {
        "mypy": "2.1.0"
      }
    },
    {
      "at": "2026-06-12T11:59:48.367960Z",
      "command": "pytest tests/architecture/ -v --no-cov",
      "covered_surface": "architecture",
      "exit_code": 0,
      "input_fingerprint": "sha256:5ede1d49fb8dfd78571108ce39ef8fc8ce6d3cd58fe19c86493cffdc1f875f99",
      "name": "architecture_tests",
      "parity_detail": null,
      "parity_gap": false,
      "pr_only": false,
      "raw_log_ref": ".workflow/local/logs/architecture_tests.log",
      "status": "pass",
      "summary": "clean",
      "tool_versions": {}
    },
    {
      "at": "2026-06-12T11:59:48.403854Z",
      "command": "ruff format --check .",
      "covered_surface": "python",
      "exit_code": 0,
      "input_fingerprint": "sha256:5ede1d49fb8dfd78571108ce39ef8fc8ce6d3cd58fe19c86493cffdc1f875f99",
      "name": "format_check",
      "parity_detail": null,
      "parity_gap": false,
      "pr_only": false,
      "raw_log_ref": ".workflow/local/logs/format_check.log",
      "status": "pass",
      "summary": "clean",
      "tool_versions": {
        "ruff": "0.15.15"
      }
    },
    {
      "at": "2026-06-12T11:59:56.510955Z",
      "command": "python -m scistudio.qa.audit.full_audit --repo-root . --format json --output .audit/full-audit.json",
      "covered_surface": "governance",
      "exit_code": 0,
      "input_fingerprint": "sha256:5ede1d49fb8dfd78571108ce39ef8fc8ce6d3cd58fe19c86493cffdc1f875f99",
      "name": "full_audit",
      "parity_detail": null,
      "parity_gap": false,
      "pr_only": false,
      "raw_log_ref": ".workflow/local/logs/full_audit.log",
      "status": "pass",
      "summary": "clean",
      "tool_versions": {}
    },
    {
      "at": "2026-06-12T11:59:56.722132Z",
      "command": "lint-imports",
      "covered_surface": "python",
      "exit_code": 0,
      "input_fingerprint": "sha256:5ede1d49fb8dfd78571108ce39ef8fc8ce6d3cd58fe19c86493cffdc1f875f99",
      "name": "import_contracts",
      "parity_detail": null,
      "parity_gap": false,
      "pr_only": false,
      "raw_log_ref": ".workflow/local/logs/import_contracts.log",
      "status": "pass",
      "summary": "clean",
      "tool_versions": {}
    },
    {
      "at": "2026-06-12T11:59:56.755734Z",
      "command": "ruff check .",
      "covered_surface": "python",
      "exit_code": 0,
      "input_fingerprint": "sha256:5ede1d49fb8dfd78571108ce39ef8fc8ce6d3cd58fe19c86493cffdc1f875f99",
      "name": "lint_format",
      "parity_detail": null,
      "parity_gap": false,
      "pr_only": false,
      "raw_log_ref": ".workflow/local/logs/lint_format.log",
      "status": "pass",
      "summary": "clean",
      "tool_versions": {
        "ruff": "0.15.15"
      }
    },
    {
      "at": "2026-06-12T12:02:04.610193Z",
      "command": "pytest -n auto --timeout=60 --timeout-method=thread",
      "covered_surface": "python",
      "exit_code": 0,
      "input_fingerprint": "sha256:5ede1d49fb8dfd78571108ce39ef8fc8ce6d3cd58fe19c86493cffdc1f875f99",
      "name": "python_tests",
      "parity_detail": null,
      "parity_gap": false,
      "pr_only": false,
      "raw_log_ref": ".workflow/local/logs/python_tests.log",
      "status": "pass",
      "summary": "clean",
      "tool_versions": {}
    },
    {
      "at": "2026-06-12T12:02:50.761037Z",
      "command": "python scripts/semantic_dup_scan.py --check docs/audit/baselines/semantic-dup-baseline.json",
      "covered_surface": "python",
      "exit_code": 0,
      "input_fingerprint": "sha256:5ede1d49fb8dfd78571108ce39ef8fc8ce6d3cd58fe19c86493cffdc1f875f99",
      "name": "semantic_dup",
      "parity_detail": null,
      "parity_gap": false,
      "pr_only": false,
      "raw_log_ref": ".workflow/local/logs/semantic_dup.log",
      "status": "pass",
      "summary": "clean",
      "tool_versions": {}
    },
    {
      "at": "2026-06-12T12:02:51.389792Z",
      "command": "mypy src/scistudio/ --ignore-missing-imports",
      "covered_surface": "python",
      "exit_code": 0,
      "input_fingerprint": "sha256:5ede1d49fb8dfd78571108ce39ef8fc8ce6d3cd58fe19c86493cffdc1f875f99",
      "name": "type_check",
      "parity_detail": null,
      "parity_gap": false,
      "pr_only": false,
      "raw_log_ref": ".workflow/local/logs/type_check.log",
      "status": "pass",
      "summary": "clean",
      "tool_versions": {
        "mypy": "2.1.0"
      }
    }
  ],
  "check_na": [],
  "commit": {
    "sha": "3c5625bd1b11e85a1a098655179e4040e2724c3f",
    "shas": [
      "3c5625bd1b11e85a1a098655179e4040e2724c3f"
    ],
    "trailers": []
  },
  "declared_scope": {
    "exclude": [],
    "include": []
  },
  "directive_events": [],
  "docs_events": [
    {
      "at": "2026-06-12T10:26:34.418180Z",
      "class": null,
      "kind": "path",
      "path": "CHANGELOG.md",
      "rationale": null,
      "verified_in_diff": null
    },
    {
      "at": "2026-06-12T10:26:34.418186Z",
      "class": null,
      "kind": "path",
      "path": "docs/specs/adr-042-gate-ledger-runtime.md",
      "rationale": null,
      "verified_in_diff": null
    }
  ],
  "governance_touch": true,
  "guard_events": [
    {
      "at": "2026-06-12T09:31:47.350887Z",
      "findings": [],
      "guard": "core_change_guard",
      "status": "pass"
    },
    {
      "at": "2026-06-12T09:31:47.392877Z",
      "findings": [],
      "guard": "docs_landing",
      "status": "pass"
    },
    {
      "at": "2026-06-12T09:31:47.436556Z",
      "findings": [],
      "guard": "human_bypass_guard",
      "status": "pass"
    },
    {
      "at": "2026-06-12T09:31:47.474464Z",
      "findings": [],
      "guard": "issue_link",
      "status": "pass"
    },
    {
      "at": "2026-06-12T09:31:47.513604Z",
      "findings": [],
      "guard": "mod_guard",
      "status": "pass"
    },
    {
      "at": "2026-06-12T09:31:47.551976Z",
      "findings": [],
      "guard": "persona_policy",
      "status": "pass"
    },
    {
      "at": "2026-06-12T09:31:47.594802Z",
      "findings": [],
      "guard": "pr_merge_guard",
      "status": "pass"
    },
    {
      "at": "2026-06-12T09:31:47.635476Z",
      "findings": [],
      "guard": "sentrux_gate",
      "status": "pass"
    },
    {
      "at": "2026-06-12T09:31:47.672421Z",
      "findings": [],
      "guard": "test_engineer_scope_guard",
      "status": "pass"
    },
    {
      "at": "2026-06-12T09:31:47.708619Z",
      "findings": [],
      "guard": "weakened_ci_check",
      "status": "pass"
    },
    {
      "at": "2026-06-12T09:43:36.411964Z",
      "findings": [],
      "guard": "core_change_guard",
      "status": "pass"
    },
    {
      "at": "2026-06-12T09:43:36.457152Z",
      "findings": [],
      "guard": "docs_landing",
      "status": "pass"
    },
    {
      "at": "2026-06-12T09:43:36.500648Z",
      "findings": [],
      "guard": "human_bypass_guard",
      "status": "pass"
    },
    {
      "at": "2026-06-12T09:43:36.550021Z",
      "findings": [],
      "guard": "issue_link",
      "status": "pass"
    },
    {
      "at": "2026-06-12T09:43:36.601062Z",
      "findings": [],
      "guard": "mod_guard",
      "status": "pass"
    },
    {
      "at": "2026-06-12T09:43:36.644363Z",
      "findings": [],
      "guard": "persona_policy",
      "status": "pass"
    },
    {
      "at": "2026-06-12T09:43:36.693577Z",
      "findings": [],
      "guard": "pr_merge_guard",
      "status": "pass"
    },
    {
      "at": "2026-06-12T09:43:36.737619Z",
      "findings": [],
      "guard": "sentrux_gate",
      "status": "pass"
    },
    {
      "at": "2026-06-12T09:43:36.781298Z",
      "findings": [],
      "guard": "test_engineer_scope_guard",
      "status": "pass"
    },
    {
      "at": "2026-06-12T09:43:36.829541Z",
      "findings": [],
      "guard": "weakened_ci_check",
      "status": "pass"
    },
    {
      "at": "2026-06-12T09:45:07.405490Z",
      "findings": [],
      "guard": "core_change_guard",
      "status": "pass"
    },
    {
      "at": "2026-06-12T09:45:07.448602Z",
      "findings": [],
      "guard": "docs_landing",
      "status": "pass"
    },
    {
      "at": "2026-06-12T09:45:07.491435Z",
      "findings": [],
      "guard": "human_bypass_guard",
      "status": "pass"
    },
    {
      "at": "2026-06-12T09:45:07.542363Z",
      "findings": [],
      "guard": "issue_link",
      "status": "pass"
    },
    {
      "at": "2026-06-12T09:45:07.585373Z",
      "findings": [],
      "guard": "mod_guard",
      "status": "pass"
    },
    {
      "at": "2026-06-12T09:45:07.630048Z",
      "findings": [],
      "guard": "persona_policy",
      "status": "pass"
    },
    {
      "at": "2026-06-12T09:45:07.673853Z",
      "findings": [],
      "guard": "pr_merge_guard",
      "status": "pass"
    },
    {
      "at": "2026-06-12T09:45:07.715460Z",
      "findings": [],
      "guard": "sentrux_gate",
      "status": "pass"
    },
    {
      "at": "2026-06-12T09:45:07.759202Z",
      "findings": [],
      "guard": "test_engineer_scope_guard",
      "status": "pass"
    },
    {
      "at": "2026-06-12T09:45:07.803074Z",
      "findings": [],
      "guard": "weakened_ci_check",
      "status": "pass"
    },
    {
      "at": "2026-06-12T09:48:00.858191Z",
      "findings": [],
      "guard": "core_change_guard",
      "status": "pass"
    },
    {
      "at": "2026-06-12T09:48:00.902274Z",
      "findings": [],
      "guard": "docs_landing",
      "status": "pass"
    },
    {
      "at": "2026-06-12T09:48:00.947068Z",
      "findings": [],
      "guard": "human_bypass_guard",
      "status": "pass"
    },
    {
      "at": "2026-06-12T09:48:01.014412Z",
      "findings": [],
      "guard": "issue_link",
      "status": "pass"
    },
    {
      "at": "2026-06-12T09:48:01.059297Z",
      "findings": [],
      "guard": "mod_guard",
      "status": "pass"
    },
    {
      "at": "2026-06-12T09:48:01.104547Z",
      "findings": [],
      "guard": "persona_policy",
      "status": "pass"
    },
    {
      "at": "2026-06-12T09:48:01.149695Z",
      "findings": [],
      "guard": "pr_merge_guard",
      "status": "pass"
    },
    {
      "at": "2026-06-12T09:48:01.199410Z",
      "findings": [],
      "guard": "sentrux_gate",
      "status": "pass"
    },
    {
      "at": "2026-06-12T09:48:01.242027Z",
      "findings": [],
      "guard": "test_engineer_scope_guard",
      "status": "pass"
    },
    {
      "at": "2026-06-12T09:48:01.284947Z",
      "findings": [],
      "guard": "weakened_ci_check",
      "status": "pass"
    },
    {
      "at": "2026-06-12T09:52:05.887168Z",
      "findings": [],
      "guard": "core_change_guard",
      "status": "pass"
    },
    {
      "at": "2026-06-12T09:52:05.931433Z",
      "findings": [],
      "guard": "docs_landing",
      "status": "pass"
    },
    {
      "at": "2026-06-12T09:52:05.976125Z",
      "findings": [],
      "guard": "human_bypass_guard",
      "status": "pass"
    },
    {
      "at": "2026-06-12T09:52:06.019960Z",
      "findings": [],
      "guard": "issue_link",
      "status": "pass"
    },
    {
      "at": "2026-06-12T09:52:06.064149Z",
      "findings": [],
      "guard": "mod_guard",
      "status": "pass"
    },
    {
      "at": "2026-06-12T09:52:06.118853Z",
      "findings": [],
      "guard": "persona_policy",
      "status": "pass"
    },
    {
      "at": "2026-06-12T09:52:06.161583Z",
      "findings": [],
      "guard": "pr_merge_guard",
      "status": "pass"
    },
    {
      "at": "2026-06-12T09:52:06.210916Z",
      "findings": [],
      "guard": "sentrux_gate",
      "status": "pass"
    },
    {
      "at": "2026-06-12T09:52:06.254017Z",
      "findings": [],
      "guard": "test_engineer_scope_guard",
      "status": "pass"
    },
    {
      "at": "2026-06-12T09:52:06.295168Z",
      "findings": [],
      "guard": "weakened_ci_check",
      "status": "pass"
    },
    {
      "at": "2026-06-12T10:03:15.088387Z",
      "findings": [
        {
          "actual": null,
          "drift_class": null,
          "evidence": {},
          "expected": null,
          "file": "src/scistudio/utils/git_env.py",
          "finding_class": "core_change_guard",
          "git_evidence": null,
          "id": "core_change_guard.missing-admin-approval",
          "line": null,
          "message": "protected core/runtime change requires admin-approved:core-change applied by an authorized maintainer or administrator approval",
          "path": "src/scistudio/utils/git_env.py",
          "related_findings": [],
          "remediation": null,
          "rule_id": "core_change_guard.missing-admin-approval",
          "severity": "error",
          "subject": null,
          "suggested_fix": null,
          "symbol": null,
          "tool": null
        }
      ],
      "guard": "core_change_guard",
      "status": "fail"
    },
    {
      "at": "2026-06-12T10:03:15.135309Z",
      "findings": [
        {
          "actual": null,
          "drift_class": null,
          "evidence": {
            "governed_files": [
              ".pre-commit-config.yaml",
              "scripts/hooks/run_python_module.py",
              "src/scistudio/utils/git_env.py"
            ]
          },
          "expected": null,
          "file": "",
          "finding_class": "docs_landing",
          "git_evidence": null,
          "id": "docs_landing.missing-landing",
          "line": null,
          "message": "governed change requires docs/changelog/checklist landing evidence or an explicit N/A rationale",
          "path": "",
          "related_findings": [],
          "remediation": null,
          "rule_id": "docs_landing.missing-landing",
          "severity": "error",
          "subject": null,
          "suggested_fix": null,
          "symbol": null,
          "tool": null
        }
      ],
      "guard": "docs_landing",
      "status": "fail"
    },
    {
      "at": "2026-06-12T10:03:15.182270Z",
      "findings": [],
      "guard": "human_bypass_guard",
      "status": "pass"
    },
    {
      "at": "2026-06-12T10:03:15.228556Z",
      "findings": [],
      "guard": "issue_link",
      "status": "pass"
    },
    {
      "at": "2026-06-12T10:03:15.282277Z",
      "findings": [
        {
          "actual": null,
          "drift_class": null,
          "evidence": {},
          "expected": null,
          "file": ".pre-commit-config.yaml",
          "finding_class": "governance",
          "git_evidence": null,
          "id": "governance.mod_guard.unauthorized-change",
          "line": null,
          "message": "governance-critical file changed without authorization; declare governance_touch in the ledger and obtain owner review",
          "path": ".pre-commit-config.yaml",
          "related_findings": [],
          "remediation": null,
          "rule_id": "governance.mod_guard.unauthorized-change",
          "severity": "error",
          "subject": null,
          "suggested_fix": null,
          "symbol": null,
          "tool": null
        }
      ],
      "guard": "mod_guard",
      "status": "fail"
    },
    {
      "at": "2026-06-12T10:03:15.330237Z",
      "findings": [],
      "guard": "persona_policy",
      "status": "pass"
    },
    {
      "at": "2026-06-12T10:03:15.379217Z",
      "findings": [],
      "guard": "pr_merge_guard",
      "status": "pass"
    },
    {
      "at": "2026-06-12T10:03:15.428219Z",
      "findings": [
        {
          "actual": null,
          "drift_class": null,
          "evidence": {},
          "expected": null,
          "file": "",
          "finding_class": "sentrux",
          "git_evidence": null,
          "id": "sentrux.free_tier.advisory-missing-evidence",
          "line": null,
          "message": "Sentrux evidence is recommended for source/workflow/architecture changes (advisory, opt-in).",
          "path": "",
          "related_findings": [],
          "remediation": null,
          "rule_id": "sentrux.free_tier.advisory-missing-evidence",
          "severity": "info",
          "subject": null,
          "suggested_fix": null,
          "symbol": null,
          "tool": null
        }
      ],
      "guard": "sentrux_gate",
      "status": "pass"
    },
    {
      "at": "2026-06-12T10:03:15.477533Z",
      "findings": [],
      "guard": "test_engineer_scope_guard",
      "status": "pass"
    },
    {
      "at": "2026-06-12T10:03:15.530435Z",
      "findings": [],
      "guard": "weakened_ci_check",
      "status": "pass"
    },
    {
      "at": "2026-06-12T10:15:47.147264Z",
      "findings": [
        {
          "actual": null,
          "drift_class": null,
          "evidence": {},
          "expected": null,
          "file": "src/scistudio/utils/git_env.py",
          "finding_class": "core_change_guard",
          "git_evidence": null,
          "id": "core_change_guard.missing-admin-approval",
          "line": null,
          "message": "protected core/runtime change requires admin-approved:core-change applied by an authorized maintainer or administrator approval",
          "path": "src/scistudio/utils/git_env.py",
          "related_findings": [],
          "remediation": null,
          "rule_id": "core_change_guard.missing-admin-approval",
          "severity": "error",
          "subject": null,
          "suggested_fix": null,
          "symbol": null,
          "tool": null
        }
      ],
      "guard": "core_change_guard",
      "status": "fail"
    },
    {
      "at": "2026-06-12T10:15:47.194595Z",
      "findings": [
        {
          "actual": null,
          "drift_class": null,
          "evidence": {
            "governed_files": [
              ".pre-commit-config.yaml",
              "scripts/hooks/run_python_module.py",
              "src/scistudio/utils/git_env.py"
            ]
          },
          "expected": null,
          "file": "",
          "finding_class": "docs_landing",
          "git_evidence": null,
          "id": "docs_landing.missing-landing",
          "line": null,
          "message": "governed change requires docs/changelog/checklist landing evidence or an explicit N/A rationale",
          "path": "",
          "related_findings": [],
          "remediation": null,
          "rule_id": "docs_landing.missing-landing",
          "severity": "error",
          "subject": null,
          "suggested_fix": null,
          "symbol": null,
          "tool": null
        }
      ],
      "guard": "docs_landing",
      "status": "fail"
    },
    {
      "at": "2026-06-12T10:15:47.250453Z",
      "findings": [],
      "guard": "human_bypass_guard",
      "status": "pass"
    },
    {
      "at": "2026-06-12T10:15:47.298562Z",
      "findings": [],
      "guard": "issue_link",
      "status": "pass"
    },
    {
      "at": "2026-06-12T10:15:47.352077Z",
      "findings": [
        {
          "actual": null,
          "drift_class": null,
          "evidence": {},
          "expected": null,
          "file": ".pre-commit-config.yaml",
          "finding_class": "governance",
          "git_evidence": null,
          "id": "governance.mod_guard.unauthorized-change",
          "line": null,
          "message": "governance-critical file changed without authorization; declare governance_touch in the ledger and obtain owner review",
          "path": ".pre-commit-config.yaml",
          "related_findings": [],
          "remediation": null,
          "rule_id": "governance.mod_guard.unauthorized-change",
          "severity": "error",
          "subject": null,
          "suggested_fix": null,
          "symbol": null,
          "tool": null
        }
      ],
      "guard": "mod_guard",
      "status": "fail"
    },
    {
      "at": "2026-06-12T10:15:47.399424Z",
      "findings": [],
      "guard": "persona_policy",
      "status": "pass"
    },
    {
      "at": "2026-06-12T10:15:47.446511Z",
      "findings": [],
      "guard": "pr_merge_guard",
      "status": "pass"
    },
    {
      "at": "2026-06-12T10:15:47.502223Z",
      "findings": [
        {
          "actual": null,
          "drift_class": null,
          "evidence": {},
          "expected": null,
          "file": "",
          "finding_class": "sentrux",
          "git_evidence": null,
          "id": "sentrux.free_tier.advisory-missing-evidence",
          "line": null,
          "message": "Sentrux evidence is recommended for source/workflow/architecture changes (advisory, opt-in).",
          "path": "",
          "related_findings": [],
          "remediation": null,
          "rule_id": "sentrux.free_tier.advisory-missing-evidence",
          "severity": "info",
          "subject": null,
          "suggested_fix": null,
          "symbol": null,
          "tool": null
        }
      ],
      "guard": "sentrux_gate",
      "status": "pass"
    },
    {
      "at": "2026-06-12T10:15:47.549969Z",
      "findings": [],
      "guard": "test_engineer_scope_guard",
      "status": "pass"
    },
    {
      "at": "2026-06-12T10:15:47.597698Z",
      "findings": [],
      "guard": "weakened_ci_check",
      "status": "pass"
    },
    {
      "at": "2026-06-12T10:19:45.880645Z",
      "findings": [
        {
          "actual": null,
          "drift_class": null,
          "evidence": {},
          "expected": null,
          "file": "src/scistudio/utils/git_env.py",
          "finding_class": "core_change_guard",
          "git_evidence": null,
          "id": "core_change_guard.missing-admin-approval",
          "line": null,
          "message": "protected core/runtime change requires admin-approved:core-change applied by an authorized maintainer or administrator approval",
          "path": "src/scistudio/utils/git_env.py",
          "related_findings": [],
          "remediation": null,
          "rule_id": "core_change_guard.missing-admin-approval",
          "severity": "error",
          "subject": null,
          "suggested_fix": null,
          "symbol": null,
          "tool": null
        }
      ],
      "guard": "core_change_guard",
      "status": "fail"
    },
    {
      "at": "2026-06-12T10:19:45.923003Z",
      "findings": [
        {
          "actual": null,
          "drift_class": null,
          "evidence": {
            "governed_files": [
              ".pre-commit-config.yaml",
              "scripts/hooks/run_python_module.py",
              "src/scistudio/utils/git_env.py"
            ]
          },
          "expected": null,
          "file": "",
          "finding_class": "docs_landing",
          "git_evidence": null,
          "id": "docs_landing.missing-landing",
          "line": null,
          "message": "governed change requires docs/changelog/checklist landing evidence or an explicit N/A rationale",
          "path": "",
          "related_findings": [],
          "remediation": null,
          "rule_id": "docs_landing.missing-landing",
          "severity": "error",
          "subject": null,
          "suggested_fix": null,
          "symbol": null,
          "tool": null
        }
      ],
      "guard": "docs_landing",
      "status": "fail"
    },
    {
      "at": "2026-06-12T10:19:45.964706Z",
      "findings": [],
      "guard": "human_bypass_guard",
      "status": "pass"
    },
    {
      "at": "2026-06-12T10:19:46.016579Z",
      "findings": [],
      "guard": "issue_link",
      "status": "pass"
    },
    {
      "at": "2026-06-12T10:19:46.060329Z",
      "findings": [
        {
          "actual": null,
          "drift_class": null,
          "evidence": {},
          "expected": null,
          "file": ".pre-commit-config.yaml",
          "finding_class": "governance",
          "git_evidence": null,
          "id": "governance.mod_guard.unauthorized-change",
          "line": null,
          "message": "governance-critical file changed without authorization; declare governance_touch in the ledger and obtain owner review",
          "path": ".pre-commit-config.yaml",
          "related_findings": [],
          "remediation": null,
          "rule_id": "governance.mod_guard.unauthorized-change",
          "severity": "error",
          "subject": null,
          "suggested_fix": null,
          "symbol": null,
          "tool": null
        }
      ],
      "guard": "mod_guard",
      "status": "fail"
    },
    {
      "at": "2026-06-12T10:19:46.111134Z",
      "findings": [],
      "guard": "persona_policy",
      "status": "pass"
    },
    {
      "at": "2026-06-12T10:19:46.155022Z",
      "findings": [],
      "guard": "pr_merge_guard",
      "status": "pass"
    },
    {
      "at": "2026-06-12T10:19:46.199183Z",
      "findings": [
        {
          "actual": null,
          "drift_class": null,
          "evidence": {},
          "expected": null,
          "file": "",
          "finding_class": "sentrux",
          "git_evidence": null,
          "id": "sentrux.free_tier.advisory-missing-evidence",
          "line": null,
          "message": "Sentrux evidence is recommended for source/workflow/architecture changes (advisory, opt-in).",
          "path": "",
          "related_findings": [],
          "remediation": null,
          "rule_id": "sentrux.free_tier.advisory-missing-evidence",
          "severity": "info",
          "subject": null,
          "suggested_fix": null,
          "symbol": null,
          "tool": null
        }
      ],
      "guard": "sentrux_gate",
      "status": "pass"
    },
    {
      "at": "2026-06-12T10:19:46.242936Z",
      "findings": [],
      "guard": "test_engineer_scope_guard",
      "status": "pass"
    },
    {
      "at": "2026-06-12T10:19:46.285929Z",
      "findings": [],
      "guard": "weakened_ci_check",
      "status": "pass"
    },
    {
      "at": "2026-06-12T10:30:07.068924Z",
      "findings": [],
      "guard": "core_change_guard",
      "status": "pass"
    },
    {
      "at": "2026-06-12T10:30:07.114946Z",
      "findings": [],
      "guard": "docs_landing",
      "status": "pass"
    },
    {
      "at": "2026-06-12T10:30:07.161096Z",
      "findings": [],
      "guard": "human_bypass_guard",
      "status": "pass"
    },
    {
      "at": "2026-06-12T10:30:07.207354Z",
      "findings": [],
      "guard": "issue_link",
      "status": "pass"
    },
    {
      "at": "2026-06-12T10:30:07.253594Z",
      "findings": [],
      "guard": "mod_guard",
      "status": "pass"
    },
    {
      "at": "2026-06-12T10:30:07.299521Z",
      "findings": [],
      "guard": "persona_policy",
      "status": "pass"
    },
    {
      "at": "2026-06-12T10:30:07.345991Z",
      "findings": [],
      "guard": "pr_merge_guard",
      "status": "pass"
    },
    {
      "at": "2026-06-12T10:30:07.392367Z",
      "findings": [
        {
          "actual": null,
          "drift_class": null,
          "evidence": {},
          "expected": null,
          "file": "",
          "finding_class": "sentrux",
          "git_evidence": null,
          "id": "sentrux.free_tier.advisory-missing-evidence",
          "line": null,
          "message": "Sentrux evidence is recommended for source/workflow/architecture changes (advisory, opt-in).",
          "path": "",
          "related_findings": [],
          "remediation": null,
          "rule_id": "sentrux.free_tier.advisory-missing-evidence",
          "severity": "info",
          "subject": null,
          "suggested_fix": null,
          "symbol": null,
          "tool": null
        }
      ],
      "guard": "sentrux_gate",
      "status": "pass"
    },
    {
      "at": "2026-06-12T10:30:07.438778Z",
      "findings": [],
      "guard": "test_engineer_scope_guard",
      "status": "pass"
    },
    {
      "at": "2026-06-12T10:30:07.495188Z",
      "findings": [],
      "guard": "weakened_ci_check",
      "status": "pass"
    },
    {
      "at": "2026-06-12T10:33:39.262224Z",
      "findings": [],
      "guard": "core_change_guard",
      "status": "pass"
    },
    {
      "at": "2026-06-12T10:33:39.309166Z",
      "findings": [],
      "guard": "docs_landing",
      "status": "pass"
    },
    {
      "at": "2026-06-12T10:33:39.356753Z",
      "findings": [],
      "guard": "human_bypass_guard",
      "status": "pass"
    },
    {
      "at": "2026-06-12T10:33:39.404103Z",
      "findings": [],
      "guard": "issue_link",
      "status": "pass"
    },
    {
      "at": "2026-06-12T10:33:39.450498Z",
      "findings": [],
      "guard": "mod_guard",
      "status": "pass"
    },
    {
      "at": "2026-06-12T10:33:39.499535Z",
      "findings": [],
      "guard": "persona_policy",
      "status": "pass"
    },
    {
      "at": "2026-06-12T10:33:39.549008Z",
      "findings": [],
      "guard": "pr_merge_guard",
      "status": "pass"
    },
    {
      "at": "2026-06-12T10:33:39.600129Z",
      "findings": [
        {
          "actual": null,
          "drift_class": null,
          "evidence": {},
          "expected": null,
          "file": "",
          "finding_class": "sentrux",
          "git_evidence": null,
          "id": "sentrux.free_tier.advisory-missing-evidence",
          "line": null,
          "message": "Sentrux evidence is recommended for source/workflow/architecture changes (advisory, opt-in).",
          "path": "",
          "related_findings": [],
          "remediation": null,
          "rule_id": "sentrux.free_tier.advisory-missing-evidence",
          "severity": "info",
          "subject": null,
          "suggested_fix": null,
          "symbol": null,
          "tool": null
        }
      ],
      "guard": "sentrux_gate",
      "status": "pass"
    },
    {
      "at": "2026-06-12T10:33:39.651201Z",
      "findings": [],
      "guard": "test_engineer_scope_guard",
      "status": "pass"
    },
    {
      "at": "2026-06-12T10:33:39.705347Z",
      "findings": [],
      "guard": "weakened_ci_check",
      "status": "pass"
    },
    {
      "at": "2026-06-12T11:38:24.854147Z",
      "findings": [],
      "guard": "core_change_guard",
      "status": "pass"
    },
    {
      "at": "2026-06-12T11:38:24.904912Z",
      "findings": [],
      "guard": "docs_landing",
      "status": "pass"
    },
    {
      "at": "2026-06-12T11:38:24.950121Z",
      "findings": [],
      "guard": "human_bypass_guard",
      "status": "pass"
    },
    {
      "at": "2026-06-12T11:38:24.996766Z",
      "findings": [],
      "guard": "issue_link",
      "status": "pass"
    },
    {
      "at": "2026-06-12T11:38:25.042417Z",
      "findings": [],
      "guard": "mod_guard",
      "status": "pass"
    },
    {
      "at": "2026-06-12T11:38:25.096250Z",
      "findings": [],
      "guard": "persona_policy",
      "status": "pass"
    },
    {
      "at": "2026-06-12T11:38:25.144782Z",
      "findings": [],
      "guard": "pr_merge_guard",
      "status": "pass"
    },
    {
      "at": "2026-06-12T11:38:25.191882Z",
      "findings": [
        {
          "actual": null,
          "drift_class": null,
          "evidence": {},
          "expected": null,
          "file": "",
          "finding_class": "sentrux",
          "git_evidence": null,
          "id": "sentrux.free_tier.advisory-missing-evidence",
          "line": null,
          "message": "Sentrux evidence is recommended for source/workflow/architecture changes (advisory, opt-in).",
          "path": "",
          "related_findings": [],
          "remediation": null,
          "rule_id": "sentrux.free_tier.advisory-missing-evidence",
          "severity": "info",
          "subject": null,
          "suggested_fix": null,
          "symbol": null,
          "tool": null
        }
      ],
      "guard": "sentrux_gate",
      "status": "pass"
    },
    {
      "at": "2026-06-12T11:38:25.235115Z",
      "findings": [],
      "guard": "test_engineer_scope_guard",
      "status": "pass"
    },
    {
      "at": "2026-06-12T11:38:25.278909Z",
      "findings": [],
      "guard": "weakened_ci_check",
      "status": "pass"
    },
    {
      "at": "2026-06-12T11:45:01.856672Z",
      "findings": [],
      "guard": "core_change_guard",
      "status": "pass"
    },
    {
      "at": "2026-06-12T11:45:01.899071Z",
      "findings": [],
      "guard": "docs_landing",
      "status": "pass"
    },
    {
      "at": "2026-06-12T11:45:01.941861Z",
      "findings": [],
      "guard": "human_bypass_guard",
      "status": "pass"
    },
    {
      "at": "2026-06-12T11:45:01.988240Z",
      "findings": [],
      "guard": "issue_link",
      "status": "pass"
    },
    {
      "at": "2026-06-12T11:45:02.032706Z",
      "findings": [],
      "guard": "mod_guard",
      "status": "pass"
    },
    {
      "at": "2026-06-12T11:45:02.083229Z",
      "findings": [],
      "guard": "persona_policy",
      "status": "pass"
    },
    {
      "at": "2026-06-12T11:45:02.134711Z",
      "findings": [],
      "guard": "pr_merge_guard",
      "status": "pass"
    },
    {
      "at": "2026-06-12T11:45:02.186262Z",
      "findings": [
        {
          "actual": null,
          "drift_class": null,
          "evidence": {},
          "expected": null,
          "file": "",
          "finding_class": "sentrux",
          "git_evidence": null,
          "id": "sentrux.free_tier.advisory-missing-evidence",
          "line": null,
          "message": "Sentrux evidence is recommended for source/workflow/architecture changes (advisory, opt-in).",
          "path": "",
          "related_findings": [],
          "remediation": null,
          "rule_id": "sentrux.free_tier.advisory-missing-evidence",
          "severity": "info",
          "subject": null,
          "suggested_fix": null,
          "symbol": null,
          "tool": null
        }
      ],
      "guard": "sentrux_gate",
      "status": "pass"
    },
    {
      "at": "2026-06-12T11:45:02.233138Z",
      "findings": [],
      "guard": "test_engineer_scope_guard",
      "status": "pass"
    },
    {
      "at": "2026-06-12T11:45:02.278932Z",
      "findings": [],
      "guard": "weakened_ci_check",
      "status": "pass"
    },
    {
      "at": "2026-06-12T12:02:51.486454Z",
      "findings": [],
      "guard": "core_change_guard",
      "status": "pass"
    },
    {
      "at": "2026-06-12T12:02:51.538617Z",
      "findings": [],
      "guard": "docs_landing",
      "status": "pass"
    },
    {
      "at": "2026-06-12T12:02:51.584177Z",
      "findings": [],
      "guard": "human_bypass_guard",
      "status": "pass"
    },
    {
      "at": "2026-06-12T12:02:51.630177Z",
      "findings": [],
      "guard": "issue_link",
      "status": "pass"
    },
    {
      "at": "2026-06-12T12:02:51.683561Z",
      "findings": [],
      "guard": "mod_guard",
      "status": "pass"
    },
    {
      "at": "2026-06-12T12:02:51.729204Z",
      "findings": [],
      "guard": "persona_policy",
      "status": "pass"
    },
    {
      "at": "2026-06-12T12:02:51.774282Z",
      "findings": [],
      "guard": "pr_merge_guard",
      "status": "pass"
    },
    {
      "at": "2026-06-12T12:02:51.820551Z",
      "findings": [
        {
          "actual": null,
          "drift_class": null,
          "evidence": {},
          "expected": null,
          "file": "",
          "finding_class": "sentrux",
          "git_evidence": null,
          "id": "sentrux.free_tier.advisory-missing-evidence",
          "line": null,
          "message": "Sentrux evidence is recommended for source/workflow/architecture changes (advisory, opt-in).",
          "path": "",
          "related_findings": [],
          "remediation": null,
          "rule_id": "sentrux.free_tier.advisory-missing-evidence",
          "severity": "info",
          "subject": null,
          "suggested_fix": null,
          "symbol": null,
          "tool": null
        }
      ],
      "guard": "sentrux_gate",
      "status": "pass"
    },
    {
      "at": "2026-06-12T12:02:51.866812Z",
      "findings": [],
      "guard": "test_engineer_scope_guard",
      "status": "pass"
    },
    {
      "at": "2026-06-12T12:02:51.915018Z",
      "findings": [],
      "guard": "weakened_ci_check",
      "status": "pass"
    },
    {
      "at": "2026-06-12T12:05:47.325245Z",
      "findings": [],
      "guard": "core_change_guard",
      "status": "pass"
    },
    {
      "at": "2026-06-12T12:05:47.368671Z",
      "findings": [],
      "guard": "docs_landing",
      "status": "pass"
    },
    {
      "at": "2026-06-12T12:05:47.413143Z",
      "findings": [],
      "guard": "human_bypass_guard",
      "status": "pass"
    },
    {
      "at": "2026-06-12T12:05:47.457336Z",
      "findings": [],
      "guard": "issue_link",
      "status": "pass"
    },
    {
      "at": "2026-06-12T12:05:47.501544Z",
      "findings": [],
      "guard": "mod_guard",
      "status": "pass"
    },
    {
      "at": "2026-06-12T12:05:47.545643Z",
      "findings": [],
      "guard": "persona_policy",
      "status": "pass"
    },
    {
      "at": "2026-06-12T12:05:47.588880Z",
      "findings": [],
      "guard": "pr_merge_guard",
      "status": "pass"
    },
    {
      "at": "2026-06-12T12:05:47.639249Z",
      "findings": [
        {
          "actual": null,
          "drift_class": null,
          "evidence": {},
          "expected": null,
          "file": "",
          "finding_class": "sentrux",
          "git_evidence": null,
          "id": "sentrux.free_tier.advisory-missing-evidence",
          "line": null,
          "message": "Sentrux evidence is recommended for source/workflow/architecture changes (advisory, opt-in).",
          "path": "",
          "related_findings": [],
          "remediation": null,
          "rule_id": "sentrux.free_tier.advisory-missing-evidence",
          "severity": "info",
          "subject": null,
          "suggested_fix": null,
          "symbol": null,
          "tool": null
        }
      ],
      "guard": "sentrux_gate",
      "status": "pass"
    },
    {
      "at": "2026-06-12T12:05:47.689681Z",
      "findings": [],
      "guard": "test_engineer_scope_guard",
      "status": "pass"
    },
    {
      "at": "2026-06-12T12:05:47.734934Z",
      "findings": [],
      "guard": "weakened_ci_check",
      "status": "pass"
    }
  ],
  "issues": [
    {
      "close_in_pr": true,
      "followup_rationale": null,
      "number": 1609,
      "url": null
    }
  ],
  "observed_admin_labels": [],
  "observed_diff": {
    "base": "1b6372d41e540b96d5e3cab18692b0ca2c7cdaca",
    "base_sha": "1b6372d4",
    "changed_files": [
      ".pre-commit-config.yaml",
      ".workflow/records/1609-fix-git-env-leak-and-gate-hooks-1609.json",
      "CHANGELOG.md",
      "docs/specs/adr-042-gate-ledger-runtime.md",
      "scripts/hooks/run_python_module.py",
      "src/scistudio/qa/governance/gate_record/cli.py",
      "src/scistudio/qa/governance/gate_record/workflow.py",
      "tests/qa/test_commit_msg_hook_wiring.py",
      "tests/qa/test_gate_record.py",
      "tests/qa/test_gate_record_hooks.py",
      "tests/scripts/test_run_python_module.py"
    ],
    "diff_fingerprint": "sha256:db4a0ef70c89d26e3027632ad4f9f197556129a2acf4887e4e40684dded35697",
    "head": "HEAD",
    "head_sha": "3c5625bd",
    "surfaces": {
      "docs": 1,
      "frontend": 0,
      "governance": 3,
      "governed_docs": 0,
      "implementation": 4,
      "packaging": 0,
      "protected_core": 0,
      "sentrux": 9,
      "test": 4,
      "workflow_ci": 2
    }
  },
  "owner_directive": "Fix all four defects tracked in issue #1609: (1) P0 scrub git env (GIT_DIR/--local-env-vars + GIT_AUTHOR_*/GIT_COMMITTER_*) in the hook launcher so gate/pytest children cannot corrupt the shared .git; (2) weakened_ci_check pre-commit base-vs-staged false positive; (3) pre-push ledger discovery branch/finalized filter + --record injection; (4) commit-msg hook wiring so git commit succeeds.",
  "persona": "implementer",
  "pull_request": {
    "body_closes_issues": [],
    "closes": [
      1609
    ],
    "number": 1612,
    "url": "https://github.com/zjzcpj/SciStudio/pull/1612"
  },
  "reconcile_events": [
    {
      "at": "2026-06-12T09:31:47.708657Z",
      "diff_fingerprint": "sha256:e3b0c44298fc1c149afbf4c8996fb92427ae41e4649b934ca495991b7852b855",
      "mode": "commit-msg",
      "result": "pass",
      "tier": 2,
      "unsatisfied": []
    },
    {
      "at": "2026-06-12T09:43:36.829570Z",
      "diff_fingerprint": "sha256:e3b0c44298fc1c149afbf4c8996fb92427ae41e4649b934ca495991b7852b855",
      "mode": "pre-pr",
      "result": "fail",
      "tier": 2,
      "unsatisfied": [
        "checks.lint_format"
      ]
    },
    {
      "at": "2026-06-12T09:45:07.803112Z",
      "diff_fingerprint": "sha256:e3b0c44298fc1c149afbf4c8996fb92427ae41e4649b934ca495991b7852b855",
      "mode": "pre-pr",
      "result": "pass",
      "tier": 2,
      "unsatisfied": []
    },
    {
      "at": "2026-06-12T09:48:01.284984Z",
      "diff_fingerprint": "sha256:e3b0c44298fc1c149afbf4c8996fb92427ae41e4649b934ca495991b7852b855",
      "mode": "pre-pr",
      "result": "pass",
      "tier": 2,
      "unsatisfied": []
    },
    {
      "at": "2026-06-12T09:52:06.295204Z",
      "diff_fingerprint": "sha256:e3b0c44298fc1c149afbf4c8996fb92427ae41e4649b934ca495991b7852b855",
      "mode": "pre-pr",
      "result": "pass",
      "tier": 2,
      "unsatisfied": []
    },
    {
      "at": "2026-06-12T10:03:15.530471Z",
      "diff_fingerprint": "sha256:40c86ca27c3d3b37364115ed3327b65a49d276b7b98566e0eaeefebc548dfe4e",
      "mode": "pre-commit",
      "result": "fail",
      "tier": 1,
      "unsatisfied": [
        "docs.docs_required_or_na",
        "guard.core_change_guard",
        "guard.docs_landing",
        "guard.mod_guard",
        "tests.changed_test_required"
      ]
    },
    {
      "at": "2026-06-12T10:15:47.597733Z",
      "diff_fingerprint": "sha256:3db73c68fbcf64653b5ee388f0212ba2d71213c36b0280e1092f74e16b244caf",
      "mode": "pre-commit",
      "result": "fail",
      "tier": 1,
      "unsatisfied": [
        "docs.docs_required_or_na",
        "guard.core_change_guard",
        "guard.docs_landing",
        "guard.mod_guard",
        "tests.changed_test_required"
      ]
    },
    {
      "at": "2026-06-12T10:19:46.285965Z",
      "diff_fingerprint": "sha256:f4c7bbd16e0815606a895562affb197b0ee848a363571d2bf135ba929191f9e4",
      "mode": "pre-commit",
      "result": "fail",
      "tier": 1,
      "unsatisfied": [
        "docs.docs_required_or_na",
        "guard.core_change_guard",
        "guard.docs_landing",
        "guard.mod_guard",
        "tests.changed_test_required"
      ]
    },
    {
      "at": "2026-06-12T10:30:07.495221Z",
      "diff_fingerprint": "sha256:21fdbe4047f529d95a2d39db953946ab8e351eeb481b3b82dd8f3b11b21a52a5",
      "mode": "pre-commit",
      "result": "pass",
      "tier": 1,
      "unsatisfied": []
    },
    {
      "at": "2026-06-12T10:33:39.705383Z",
      "diff_fingerprint": "sha256:9e9f543c5cf49edd7712eabae57c4386de103545e7a81de78d47ebddd0c2b8cc",
      "mode": "pre-commit",
      "result": "pass",
      "tier": 1,
      "unsatisfied": []
    },
    {
      "at": "2026-06-12T11:38:25.278943Z",
      "diff_fingerprint": "sha256:53a9ac771920a6ea74bc232564737e300f3d314cfa1bc012470f1fe4c76e68d8",
      "mode": "pre-pr",
      "result": "pass",
      "tier": 1,
      "unsatisfied": []
    },
    {
      "at": "2026-06-12T11:45:02.278969Z",
      "diff_fingerprint": "sha256:db4a0ef70c89d26e3027632ad4f9f197556129a2acf4887e4e40684dded35697",
      "mode": "pre-push",
      "result": "pass",
      "tier": 1,
      "unsatisfied": []
    },
    {
      "at": "2026-06-12T12:02:51.915052Z",
      "diff_fingerprint": "sha256:db4a0ef70c89d26e3027632ad4f9f197556129a2acf4887e4e40684dded35697",
      "mode": "pre-pr",
      "result": "pass",
      "tier": 1,
      "unsatisfied": []
    },
    {
      "at": "2026-06-12T12:05:47.734966Z",
      "diff_fingerprint": "sha256:db4a0ef70c89d26e3027632ad4f9f197556129a2acf4887e4e40684dded35697",
      "mode": "ci",
      "result": "pass",
      "tier": 1,
      "unsatisfied": []
    }
  ],
  "record_id": "1609-fix-git-env-leak-and-gate-hooks-1609",
  "requested_admin_labels": [],
  "required_obligations": {
    "admin_labels": [],
    "checks": [],
    "docs": [
      "docs_required_or_na"
    ],
    "guards": [
      "core_change_guard",
      "docs_landing",
      "human_bypass_guard",
      "issue_link",
      "mod_guard",
      "persona_policy",
      "pr_merge_guard",
      "sentrux_gate",
      "test_engineer_scope_guard",
      "weakened_ci_check"
    ],
    "tests": [
      "changed_test_required"
    ]
  },
  "runtime": "claude",
  "schema_version": 2,
  "scope_events": [
    {
      "action": "add-include",
      "at": "2026-06-12T09:30:19.755121Z",
      "pattern": "scripts/hooks/run_python_module.py",
      "reason": "plan"
    },
    {
      "action": "add-include",
      "at": "2026-06-12T09:30:19.755146Z",
      "pattern": "tests/conftest.py",
      "reason": "plan"
    },
    {
      "action": "add-include",
      "at": "2026-06-12T09:30:19.755150Z",
      "pattern": ".pre-commit-config.yaml",
      "reason": "plan"
    },
    {
      "action": "add-include",
      "at": "2026-06-12T09:30:19.755152Z",
      "pattern": "src/scistudio/qa/governance/gate_record/evaluator.py",
      "reason": "plan"
    },
    {
      "action": "add-include",
      "at": "2026-06-12T09:30:19.755153Z",
      "pattern": "src/scistudio/qa/governance/gate_record/io.py",
      "reason": "plan"
    },
    {
      "action": "add-include",
      "at": "2026-06-12T09:30:19.755155Z",
      "pattern": "src/scistudio/qa/governance/gate_record/workflow.py",
      "reason": "plan"
    },
    {
      "action": "add-include",
      "at": "2026-06-12T09:30:19.755157Z",
      "pattern": "scripts/hooks/check-gate-before-push.sh",
      "reason": "plan"
    },
    {
      "action": "add-include",
      "at": "2026-06-12T09:40:35.046595Z",
      "pattern": "src/scistudio/utils/git_env.py",
      "reason": "Narrow scope to issue #1609 Defect 1 (git-env scrub) + Defect 4 (commit-msg hook wiring) only; Defects 2 & 3 confirmed as downstream symptoms of the Defect-1 corruption (corrupted index / unborn HEAD), not independent bugs, so left unchanged."
    },
    {
      "action": "add-include",
      "at": "2026-06-12T09:40:35.046614Z",
      "pattern": "tests/utils/test_git_env.py",
      "reason": "Narrow scope to issue #1609 Defect 1 (git-env scrub) + Defect 4 (commit-msg hook wiring) only; Defects 2 & 3 confirmed as downstream symptoms of the Defect-1 corruption (corrupted index / unborn HEAD), not independent bugs, so left unchanged."
    },
    {
      "action": "add-include",
      "at": "2026-06-12T09:40:35.046616Z",
      "pattern": "tests/qa/test_commit_msg_hook_wiring.py",
      "reason": "Narrow scope to issue #1609 Defect 1 (git-env scrub) + Defect 4 (commit-msg hook wiring) only; Defects 2 & 3 confirmed as downstream symptoms of the Defect-1 corruption (corrupted index / unborn HEAD), not independent bugs, so left unchanged."
    },
    {
      "action": "add-include",
      "at": "2026-06-12T09:40:35.046618Z",
      "pattern": "CHANGELOG.md",
      "reason": "Narrow scope to issue #1609 Defect 1 (git-env scrub) + Defect 4 (commit-msg hook wiring) only; Defects 2 & 3 confirmed as downstream symptoms of the Defect-1 corruption (corrupted index / unborn HEAD), not independent bugs, so left unchanged."
    },
    {
      "action": "add-include",
      "at": "2026-06-12T09:46:50.171285Z",
      "pattern": "tests/qa/test_gate_record_hooks.py",
      "reason": "Update test_gate_record_hooks.py: the commit-msg hook assertion encoded the Defect-4 buggy wiring (check --mode commit-msg); assert the fixed commit-msg alias entry."
    },
    {
      "action": "add-include",
      "at": "2026-06-12T09:47:51.649210Z",
      "pattern": "docs/specs/adr-042-gate-ledger-runtime.md",
      "reason": "Update ADR-042 runtime spec hook-entry row to document the commit-msg alias and why the bare check --mode commit-msg form must not be used (Defect 4 regression guard)."
    },
    {
      "action": "add-include",
      "at": "2026-06-12T10:26:34.418158Z",
      "pattern": "tests/scripts/test_run_python_module.py",
      "reason": "Declare governance_touch for the owner-authorized .pre-commit-config.yaml change (Defect 4 commit-msg alias + mypy-hook additional_dependencies). Record docs landing (CHANGELOG + ADR-042 runtime spec) and regression-test evidence. Scrub moved from src to the launcher (hook infra, not core)."
    },
    {
      "action": "add-include",
      "at": "2026-06-12T11:14:10.703111Z",
      "pattern": "src/scistudio/qa/governance/gate_record/cli.py",
      "reason": "Add gate_record --no-record flag (cli.py + workflow.py) so the pre-commit/commit-msg git hooks gate without persisting the ledger, fixing the pre-commit-framework 'files were modified' deadlock (#1609); regression tests in test_gate_record.py."
    },
    {
      "action": "add-include",
      "at": "2026-06-12T11:14:10.703130Z",
      "pattern": "src/scistudio/qa/governance/gate_record/workflow.py",
      "reason": "Add gate_record --no-record flag (cli.py + workflow.py) so the pre-commit/commit-msg git hooks gate without persisting the ledger, fixing the pre-commit-framework 'files were modified' deadlock (#1609); regression tests in test_gate_record.py."
    },
    {
      "action": "add-include",
      "at": "2026-06-12T11:14:10.703133Z",
      "pattern": "tests/qa/test_gate_record.py",
      "reason": "Add gate_record --no-record flag (cli.py + workflow.py) so the pre-commit/commit-msg git hooks gate without persisting the ledger, fixing the pre-commit-framework 'files were modified' deadlock (#1609); regression tests in test_gate_record.py."
    }
  ],
  "session_id": "b4ddfe2d-9359-489a-ade4-112adc0036d7",
  "strictness_tier": 1,
  "task_kind": "bugfix",
  "test_events": [
    {
      "at": "2026-06-12T10:26:34.418190Z",
      "class": null,
      "kind": "path",
      "path": "tests/scripts/test_run_python_module.py",
      "rationale": null,
      "verified_in_diff": null
    },
    {
      "at": "2026-06-12T10:26:34.418194Z",
      "class": null,
      "kind": "path",
      "path": "tests/qa/test_commit_msg_hook_wiring.py",
      "rationale": null,
      "verified_in_diff": null
    },
    {
      "at": "2026-06-12T11:14:10.703139Z",
      "class": null,
      "kind": "path",
      "path": "tests/qa/test_gate_record.py",
      "rationale": null,
      "verified_in_diff": null
    }
  ]
}
