{
  "branch": "codex/remove-alpha-registration-slack",
  "check_events": [
    {
      "at": "2026-07-07T19:16:38.779052Z",
      "command": "ruff format --check .",
      "covered_surface": "python",
      "exit_code": 0,
      "input_fingerprint": "sha256:e3b0c44298fc1c149afbf4c8996fb92427ae41e4649b934ca495991b7852b855",
      "name": "format_check",
      "parity_detail": null,
      "parity_gap": false,
      "pr_only": false,
      "raw_log_ref": ".workflow/local/logs/format_check.log",
      "status": "pass",
      "summary": "clean",
      "tool_versions": {
        "ruff": "0.15.15"
      }
    },
    {
      "at": "2026-07-07T19:16:43.211948Z",
      "command": "python -m scistudio.qa.audit.full_audit --repo-root . --format json --output .audit/full-audit.json",
      "covered_surface": "governance",
      "exit_code": 0,
      "input_fingerprint": "sha256:e3b0c44298fc1c149afbf4c8996fb92427ae41e4649b934ca495991b7852b855",
      "name": "full_audit",
      "parity_detail": null,
      "parity_gap": false,
      "pr_only": false,
      "raw_log_ref": ".workflow/local/logs/full_audit.log",
      "status": "pass",
      "summary": "clean",
      "tool_versions": {}
    },
    {
      "at": "2026-07-07T19:16:43.254533Z",
      "command": "ruff check .",
      "covered_surface": "python",
      "exit_code": 1,
      "input_fingerprint": "sha256:e3b0c44298fc1c149afbf4c8996fb92427ae41e4649b934ca495991b7852b855",
      "name": "lint_format",
      "parity_detail": null,
      "parity_gap": false,
      "pr_only": false,
      "raw_log_ref": ".workflow/local/logs/lint_format.log",
      "status": "fail",
      "summary": "exit 1",
      "tool_versions": {
        "ruff": "0.15.15"
      }
    },
    {
      "at": "2026-07-07T19:17:02.013819Z",
      "command": "ruff format --check .",
      "covered_surface": "python",
      "exit_code": 0,
      "input_fingerprint": "sha256:e3b0c44298fc1c149afbf4c8996fb92427ae41e4649b934ca495991b7852b855",
      "name": "format_check",
      "parity_detail": null,
      "parity_gap": false,
      "pr_only": false,
      "raw_log_ref": ".workflow/local/logs/format_check.log",
      "status": "pass",
      "summary": "clean",
      "tool_versions": {
        "ruff": "0.15.15"
      }
    },
    {
      "at": "2026-07-07T19:17:05.888182Z",
      "command": "python -m scistudio.qa.audit.full_audit --repo-root . --format json --output .audit/full-audit.json",
      "covered_surface": "governance",
      "exit_code": 0,
      "input_fingerprint": "sha256:e3b0c44298fc1c149afbf4c8996fb92427ae41e4649b934ca495991b7852b855",
      "name": "full_audit",
      "parity_detail": null,
      "parity_gap": false,
      "pr_only": false,
      "raw_log_ref": ".workflow/local/logs/full_audit.log",
      "status": "pass",
      "summary": "clean",
      "tool_versions": {}
    },
    {
      "at": "2026-07-07T19:17:05.902599Z",
      "command": "ruff check .",
      "covered_surface": "python",
      "exit_code": 0,
      "input_fingerprint": "sha256:e3b0c44298fc1c149afbf4c8996fb92427ae41e4649b934ca495991b7852b855",
      "name": "lint_format",
      "parity_detail": null,
      "parity_gap": false,
      "pr_only": false,
      "raw_log_ref": ".workflow/local/logs/lint_format.log",
      "status": "pass",
      "summary": "clean",
      "tool_versions": {
        "ruff": "0.15.15"
      }
    },
    {
      "at": "2026-07-07T19:17:37.063028Z",
      "command": "ruff format --check .",
      "covered_surface": "python",
      "exit_code": 0,
      "input_fingerprint": "sha256:e3b0c44298fc1c149afbf4c8996fb92427ae41e4649b934ca495991b7852b855",
      "name": "format_check",
      "parity_detail": null,
      "parity_gap": false,
      "pr_only": false,
      "raw_log_ref": ".workflow/local/logs/format_check.log",
      "status": "pass",
      "summary": "clean",
      "tool_versions": {
        "ruff": "0.15.15"
      }
    },
    {
      "at": "2026-07-07T19:17:40.955223Z",
      "command": "python -m scistudio.qa.audit.full_audit --repo-root . --format json --output .audit/full-audit.json",
      "covered_surface": "governance",
      "exit_code": 0,
      "input_fingerprint": "sha256:e3b0c44298fc1c149afbf4c8996fb92427ae41e4649b934ca495991b7852b855",
      "name": "full_audit",
      "parity_detail": null,
      "parity_gap": false,
      "pr_only": false,
      "raw_log_ref": ".workflow/local/logs/full_audit.log",
      "status": "pass",
      "summary": "clean",
      "tool_versions": {}
    },
    {
      "at": "2026-07-07T19:17:40.971148Z",
      "command": "ruff check .",
      "covered_surface": "python",
      "exit_code": 0,
      "input_fingerprint": "sha256:e3b0c44298fc1c149afbf4c8996fb92427ae41e4649b934ca495991b7852b855",
      "name": "lint_format",
      "parity_detail": null,
      "parity_gap": false,
      "pr_only": false,
      "raw_log_ref": ".workflow/local/logs/lint_format.log",
      "status": "pass",
      "summary": "clean",
      "tool_versions": {
        "ruff": "0.15.15"
      }
    },
    {
      "at": "2026-07-07T19:18:09.124172Z",
      "command": "ruff format --check .",
      "covered_surface": "python",
      "exit_code": 0,
      "input_fingerprint": "sha256:bebc350eda3ebd1aed2374645f7391915218d1aee38300323fb5110a4ab1eab5",
      "name": "format_check",
      "parity_detail": null,
      "parity_gap": false,
      "pr_only": false,
      "raw_log_ref": ".workflow/local/logs/format_check.log",
      "status": "pass",
      "summary": "clean",
      "tool_versions": {
        "ruff": "0.15.15"
      }
    },
    {
      "at": "2026-07-07T19:18:12.834422Z",
      "command": "python -m scistudio.qa.audit.full_audit --repo-root . --format json --output .audit/full-audit.json",
      "covered_surface": "governance",
      "exit_code": 0,
      "input_fingerprint": "sha256:bebc350eda3ebd1aed2374645f7391915218d1aee38300323fb5110a4ab1eab5",
      "name": "full_audit",
      "parity_detail": null,
      "parity_gap": false,
      "pr_only": false,
      "raw_log_ref": ".workflow/local/logs/full_audit.log",
      "status": "pass",
      "summary": "clean",
      "tool_versions": {}
    },
    {
      "at": "2026-07-07T19:18:13.360959Z",
      "command": "lint-imports",
      "covered_surface": "python",
      "exit_code": 0,
      "input_fingerprint": "sha256:bebc350eda3ebd1aed2374645f7391915218d1aee38300323fb5110a4ab1eab5",
      "name": "import_contracts",
      "parity_detail": null,
      "parity_gap": false,
      "pr_only": false,
      "raw_log_ref": ".workflow/local/logs/import_contracts.log",
      "status": "pass",
      "summary": "clean",
      "tool_versions": {}
    },
    {
      "at": "2026-07-07T19:18:13.376596Z",
      "command": "ruff check .",
      "covered_surface": "python",
      "exit_code": 0,
      "input_fingerprint": "sha256:bebc350eda3ebd1aed2374645f7391915218d1aee38300323fb5110a4ab1eab5",
      "name": "lint_format",
      "parity_detail": null,
      "parity_gap": false,
      "pr_only": false,
      "raw_log_ref": ".workflow/local/logs/lint_format.log",
      "status": "pass",
      "summary": "clean",
      "tool_versions": {
        "ruff": "0.15.15"
      }
    },
    {
      "at": "2026-07-07T19:20:37.482791Z",
      "command": "pytest -n auto --timeout=60 --timeout-method=thread",
      "covered_surface": "python",
      "exit_code": 1,
      "input_fingerprint": "sha256:bebc350eda3ebd1aed2374645f7391915218d1aee38300323fb5110a4ab1eab5",
      "name": "python_tests",
      "parity_detail": null,
      "parity_gap": false,
      "pr_only": false,
      "raw_log_ref": ".workflow/local/logs/python_tests.log",
      "status": "fail",
      "summary": "exit 1",
      "tool_versions": {}
    },
    {
      "at": "2026-07-07T19:22:56.006904Z",
      "command": "python scripts/semantic_dup_scan.py --check docs/audit/baselines/semantic-dup-baseline.json",
      "covered_surface": "python",
      "exit_code": 0,
      "input_fingerprint": "sha256:bebc350eda3ebd1aed2374645f7391915218d1aee38300323fb5110a4ab1eab5",
      "name": "semantic_dup",
      "parity_detail": null,
      "parity_gap": false,
      "pr_only": false,
      "raw_log_ref": ".workflow/local/logs/semantic_dup.log",
      "status": "pass",
      "summary": "clean",
      "tool_versions": {}
    },
    {
      "at": "2026-07-07T19:23:03.436541Z",
      "command": "mypy src/scistudio/ --ignore-missing-imports",
      "covered_surface": "python",
      "exit_code": 0,
      "input_fingerprint": "sha256:bebc350eda3ebd1aed2374645f7391915218d1aee38300323fb5110a4ab1eab5",
      "name": "type_check",
      "parity_detail": null,
      "parity_gap": false,
      "pr_only": false,
      "raw_log_ref": ".workflow/local/logs/type_check.log",
      "status": "pass",
      "summary": "clean",
      "tool_versions": {
        "mypy": "2.1.0"
      }
    }
  ],
  "check_na": [],
  "commit": {
    "sha": "851c782f",
    "shas": [
      "851c782f"
    ],
    "trailers": []
  },
  "declared_scope": {
    "exclude": [],
    "include": [
      "src/**",
      "desktop/**",
      "web/**",
      "docs/**",
      "tests/**",
      ".workflow/records/**"
    ]
  },
  "directive_events": [
    {
      "at": "2026-07-07T19:13:56.235114Z",
      "owner_directive": "Completely remove the alpha activation/registration gate and alpha Slack check-in notification flow.",
      "reason": "plan"
    },
    {
      "at": "2026-07-07T19:17:32.800595Z",
      "owner_directive": "Cancel Slack sending behavior as part of removing the alpha flow.",
      "reason": "Owner clarified Slack sending behavior must be cancelled, not just public Slack links."
    }
  ],
  "docs_events": [
    {
      "at": "2026-07-07T19:13:56.235463Z",
      "class": null,
      "kind": "path",
      "path": "README.md",
      "rationale": null,
      "verified_in_diff": null
    },
    {
      "at": "2026-07-07T19:13:56.235486Z",
      "class": null,
      "kind": "path",
      "path": "README.zh-CN.md",
      "rationale": null,
      "verified_in_diff": null
    },
    {
      "at": "2026-07-07T19:13:56.235488Z",
      "class": null,
      "kind": "path",
      "path": "CONTRIBUTING.md",
      "rationale": null,
      "verified_in_diff": null
    }
  ],
  "governance_touch": false,
  "guard_events": [
    {
      "at": "2026-07-07T19:16:43.278198Z",
      "findings": [],
      "guard": "core_change_guard",
      "status": "pass"
    },
    {
      "at": "2026-07-07T19:16:43.289028Z",
      "findings": [],
      "guard": "docs_landing",
      "status": "pass"
    },
    {
      "at": "2026-07-07T19:16:43.300098Z",
      "findings": [],
      "guard": "human_bypass_guard",
      "status": "pass"
    },
    {
      "at": "2026-07-07T19:16:43.311208Z",
      "findings": [],
      "guard": "issue_link",
      "status": "pass"
    },
    {
      "at": "2026-07-07T19:16:43.322702Z",
      "findings": [],
      "guard": "mod_guard",
      "status": "pass"
    },
    {
      "at": "2026-07-07T19:16:43.334025Z",
      "findings": [],
      "guard": "persona_policy",
      "status": "pass"
    },
    {
      "at": "2026-07-07T19:16:43.345278Z",
      "findings": [],
      "guard": "pr_merge_guard",
      "status": "pass"
    },
    {
      "at": "2026-07-07T19:16:43.392844Z",
      "findings": [],
      "guard": "sentrux_gate",
      "status": "pass"
    },
    {
      "at": "2026-07-07T19:16:43.408456Z",
      "findings": [],
      "guard": "test_engineer_scope_guard",
      "status": "pass"
    },
    {
      "at": "2026-07-07T19:16:43.418979Z",
      "findings": [],
      "guard": "weakened_ci_check",
      "status": "pass"
    },
    {
      "at": "2026-07-07T19:17:05.926045Z",
      "findings": [],
      "guard": "core_change_guard",
      "status": "pass"
    },
    {
      "at": "2026-07-07T19:17:05.936900Z",
      "findings": [],
      "guard": "docs_landing",
      "status": "pass"
    },
    {
      "at": "2026-07-07T19:17:05.947666Z",
      "findings": [],
      "guard": "human_bypass_guard",
      "status": "pass"
    },
    {
      "at": "2026-07-07T19:17:05.958358Z",
      "findings": [],
      "guard": "issue_link",
      "status": "pass"
    },
    {
      "at": "2026-07-07T19:17:05.970271Z",
      "findings": [],
      "guard": "mod_guard",
      "status": "pass"
    },
    {
      "at": "2026-07-07T19:17:05.981635Z",
      "findings": [],
      "guard": "persona_policy",
      "status": "pass"
    },
    {
      "at": "2026-07-07T19:17:05.993465Z",
      "findings": [],
      "guard": "pr_merge_guard",
      "status": "pass"
    },
    {
      "at": "2026-07-07T19:17:06.005805Z",
      "findings": [],
      "guard": "sentrux_gate",
      "status": "pass"
    },
    {
      "at": "2026-07-07T19:17:06.017318Z",
      "findings": [],
      "guard": "test_engineer_scope_guard",
      "status": "pass"
    },
    {
      "at": "2026-07-07T19:17:06.028224Z",
      "findings": [],
      "guard": "weakened_ci_check",
      "status": "pass"
    },
    {
      "at": "2026-07-07T19:17:40.993904Z",
      "findings": [],
      "guard": "core_change_guard",
      "status": "pass"
    },
    {
      "at": "2026-07-07T19:17:41.004826Z",
      "findings": [],
      "guard": "docs_landing",
      "status": "pass"
    },
    {
      "at": "2026-07-07T19:17:41.015611Z",
      "findings": [],
      "guard": "human_bypass_guard",
      "status": "pass"
    },
    {
      "at": "2026-07-07T19:17:41.026589Z",
      "findings": [],
      "guard": "issue_link",
      "status": "pass"
    },
    {
      "at": "2026-07-07T19:17:41.037419Z",
      "findings": [],
      "guard": "mod_guard",
      "status": "pass"
    },
    {
      "at": "2026-07-07T19:17:41.048063Z",
      "findings": [],
      "guard": "persona_policy",
      "status": "pass"
    },
    {
      "at": "2026-07-07T19:17:41.058243Z",
      "findings": [],
      "guard": "pr_merge_guard",
      "status": "pass"
    },
    {
      "at": "2026-07-07T19:17:41.068573Z",
      "findings": [],
      "guard": "sentrux_gate",
      "status": "pass"
    },
    {
      "at": "2026-07-07T19:17:41.079463Z",
      "findings": [],
      "guard": "test_engineer_scope_guard",
      "status": "pass"
    },
    {
      "at": "2026-07-07T19:17:41.090190Z",
      "findings": [],
      "guard": "weakened_ci_check",
      "status": "pass"
    },
    {
      "at": "2026-07-07T19:23:03.479541Z",
      "findings": [],
      "guard": "core_change_guard",
      "status": "pass"
    },
    {
      "at": "2026-07-07T19:23:03.490684Z",
      "findings": [],
      "guard": "docs_landing",
      "status": "pass"
    },
    {
      "at": "2026-07-07T19:23:03.501774Z",
      "findings": [],
      "guard": "human_bypass_guard",
      "status": "pass"
    },
    {
      "at": "2026-07-07T19:23:03.512859Z",
      "findings": [],
      "guard": "issue_link",
      "status": "pass"
    },
    {
      "at": "2026-07-07T19:23:03.523718Z",
      "findings": [],
      "guard": "mod_guard",
      "status": "pass"
    },
    {
      "at": "2026-07-07T19:23:03.534662Z",
      "findings": [],
      "guard": "persona_policy",
      "status": "pass"
    },
    {
      "at": "2026-07-07T19:23:03.545935Z",
      "findings": [],
      "guard": "pr_merge_guard",
      "status": "pass"
    },
    {
      "at": "2026-07-07T19:23:03.557539Z",
      "findings": [
        {
          "actual": null,
          "drift_class": null,
          "evidence": {},
          "expected": null,
          "file": "",
          "finding_class": "sentrux",
          "git_evidence": null,
          "id": "sentrux.free_tier.advisory-missing-evidence",
          "line": null,
          "message": "Sentrux evidence is recommended for source/workflow/architecture changes (advisory, opt-in).",
          "path": "",
          "related_findings": [],
          "remediation": null,
          "rule_id": "sentrux.free_tier.advisory-missing-evidence",
          "severity": "info",
          "subject": null,
          "suggested_fix": null,
          "symbol": null,
          "tool": null
        }
      ],
      "guard": "sentrux_gate",
      "status": "pass"
    },
    {
      "at": "2026-07-07T19:23:03.568440Z",
      "findings": [],
      "guard": "test_engineer_scope_guard",
      "status": "pass"
    },
    {
      "at": "2026-07-07T19:23:03.586264Z",
      "findings": [],
      "guard": "weakened_ci_check",
      "status": "pass"
    }
  ],
  "issues": [
    {
      "close_in_pr": true,
      "followup_rationale": null,
      "number": 1922,
      "url": null
    }
  ],
  "observed_admin_labels": [],
  "observed_diff": {
    "base": "origin/main",
    "base_sha": "179fad61",
    "changed_files": [
      ".workflow/records/1922-remove-alpha-registration-slack.json",
      "CONTRIBUTING.md",
      "README.md",
      "README.zh-CN.md",
      "desktop/activation.js",
      "desktop/main.js",
      "desktop/package.json",
      "desktop/preload-gate.js",
      "desktop/resources/alpha-gate.html",
      "desktop/resources/alpha-public-key.pem",
      "desktop/test/activation.test.js",
      "desktop/test/alpha-token.test.js",
      "docs/alpha-activation-gate.md",
      "scripts/alpha-token-gui.js",
      "scripts/alpha-token-issuer.command",
      "scripts/alpha-token.js",
      "scripts/build-issuer-app.sh",
      "src/scistudio/api/app.py",
      "src/scistudio/telemetry/__init__.py",
      "src/scistudio/telemetry/checkin.py",
      "tests/architecture/test_placement.py",
      "tests/packaging/test_no_alpha_gate.py",
      "tests/telemetry/test_checkin.py"
    ],
    "diff_fingerprint": "sha256:187f18c52f19d4c92eec520a7e9d77ef54fcc7be94131719ff85d1a9b7ae3887",
    "head": "HEAD",
    "head_sha": "851c782f",
    "surfaces": {
      "docs": 1,
      "frontend": 0,
      "governance": 0,
      "governed_docs": 0,
      "implementation": 3,
      "packaging": 0,
      "protected_core": 0,
      "sentrux": 6,
      "test": 5,
      "workflow_ci": 0
    }
  },
  "owner_directive": "Remove the temporary alpha registration code mechanism and Slack notification integration, then push a PR.",
  "persona": "live_implementer",
  "pull_request": {
    "body_closes_issues": [],
    "closes": [
      1922
    ],
    "number": null,
    "url": null
  },
  "reconcile_events": [
    {
      "at": "2026-07-07T19:16:43.419074Z",
      "diff_fingerprint": "sha256:e3b0c44298fc1c149afbf4c8996fb92427ae41e4649b934ca495991b7852b855",
      "mode": "pre-pr",
      "result": "fail",
      "tier": 2,
      "unsatisfied": [
        "checks.lint_format"
      ]
    },
    {
      "at": "2026-07-07T19:17:06.028274Z",
      "diff_fingerprint": "sha256:e3b0c44298fc1c149afbf4c8996fb92427ae41e4649b934ca495991b7852b855",
      "mode": "pre-pr",
      "result": "pass",
      "tier": 2,
      "unsatisfied": []
    },
    {
      "at": "2026-07-07T19:17:41.090278Z",
      "diff_fingerprint": "sha256:e3b0c44298fc1c149afbf4c8996fb92427ae41e4649b934ca495991b7852b855",
      "mode": "pre-pr",
      "result": "pass",
      "tier": 2,
      "unsatisfied": []
    },
    {
      "at": "2026-07-07T19:23:03.586301Z",
      "diff_fingerprint": "sha256:187f18c52f19d4c92eec520a7e9d77ef54fcc7be94131719ff85d1a9b7ae3887",
      "mode": "pre-pr",
      "result": "fail",
      "tier": 2,
      "unsatisfied": [
        "checks.python_tests"
      ]
    }
  ],
  "record_id": "1922-remove-alpha-registration-slack",
  "requested_admin_labels": [],
  "required_obligations": {
    "admin_labels": [],
    "checks": [
      "format_check",
      "full_audit",
      "import_contracts",
      "lint_format",
      "python_tests",
      "semantic_dup",
      "type_check"
    ],
    "docs": [
      "docs_required_or_na"
    ],
    "guards": [
      "core_change_guard",
      "docs_landing",
      "human_bypass_guard",
      "issue_link",
      "mod_guard",
      "persona_policy",
      "pr_merge_guard",
      "sentrux_gate",
      "test_engineer_scope_guard",
      "weakened_ci_check"
    ],
    "tests": [
      "changed_test_required"
    ]
  },
  "runtime": "codex",
  "schema_version": 2,
  "scope_events": [
    {
      "action": "add-include",
      "at": "2026-07-07T19:13:56.235296Z",
      "pattern": "desktop/main.js",
      "reason": "plan"
    },
    {
      "action": "add-include",
      "at": "2026-07-07T19:13:56.235304Z",
      "pattern": "desktop/package.json",
      "reason": "plan"
    },
    {
      "action": "add-include",
      "at": "2026-07-07T19:13:56.235306Z",
      "pattern": "desktop/activation.js",
      "reason": "plan"
    },
    {
      "action": "add-include",
      "at": "2026-07-07T19:13:56.235307Z",
      "pattern": "desktop/preload-gate.js",
      "reason": "plan"
    },
    {
      "action": "add-include",
      "at": "2026-07-07T19:13:56.235309Z",
      "pattern": "desktop/resources/alpha-gate.html",
      "reason": "plan"
    },
    {
      "action": "add-include",
      "at": "2026-07-07T19:13:56.235310Z",
      "pattern": "desktop/resources/alpha-public-key.pem",
      "reason": "plan"
    },
    {
      "action": "add-include",
      "at": "2026-07-07T19:13:56.235311Z",
      "pattern": "desktop/test/activation.test.js",
      "reason": "plan"
    },
    {
      "action": "add-include",
      "at": "2026-07-07T19:13:56.235312Z",
      "pattern": "desktop/test/alpha-token.test.js",
      "reason": "plan"
    },
    {
      "action": "add-include",
      "at": "2026-07-07T19:13:56.235313Z",
      "pattern": "scripts/alpha-token.js",
      "reason": "plan"
    },
    {
      "action": "add-include",
      "at": "2026-07-07T19:13:56.235314Z",
      "pattern": "scripts/alpha-token-gui.js",
      "reason": "plan"
    },
    {
      "action": "add-include",
      "at": "2026-07-07T19:13:56.235315Z",
      "pattern": "scripts/alpha-token-issuer.command",
      "reason": "plan"
    },
    {
      "action": "add-include",
      "at": "2026-07-07T19:13:56.235316Z",
      "pattern": "scripts/build-issuer-app.sh",
      "reason": "plan"
    },
    {
      "action": "add-include",
      "at": "2026-07-07T19:13:56.235317Z",
      "pattern": "src/scistudio/api/app.py",
      "reason": "plan"
    },
    {
      "action": "add-include",
      "at": "2026-07-07T19:13:56.235318Z",
      "pattern": "src/scistudio/telemetry/**",
      "reason": "plan"
    },
    {
      "action": "add-include",
      "at": "2026-07-07T19:13:56.235319Z",
      "pattern": "tests/telemetry/test_checkin.py",
      "reason": "plan"
    },
    {
      "action": "add-include",
      "at": "2026-07-07T19:13:56.235320Z",
      "pattern": "tests/architecture/test_placement.py",
      "reason": "plan"
    },
    {
      "action": "add-include",
      "at": "2026-07-07T19:13:56.235321Z",
      "pattern": "tests/packaging/test_no_alpha_gate.py",
      "reason": "plan"
    },
    {
      "action": "add-include",
      "at": "2026-07-07T19:13:56.235322Z",
      "pattern": "README.md",
      "reason": "plan"
    },
    {
      "action": "add-include",
      "at": "2026-07-07T19:13:56.235323Z",
      "pattern": "README.zh-CN.md",
      "reason": "plan"
    },
    {
      "action": "add-include",
      "at": "2026-07-07T19:13:56.235325Z",
      "pattern": "CONTRIBUTING.md",
      "reason": "plan"
    },
    {
      "action": "add-include",
      "at": "2026-07-07T19:13:56.235326Z",
      "pattern": "docs/alpha-activation-gate.md",
      "reason": "plan"
    },
    {
      "action": "add-include",
      "at": "2026-07-07T19:17:32.800778Z",
      "pattern": "desktop/main.js",
      "reason": "Owner clarified Slack sending behavior must be cancelled, not just public Slack links."
    },
    {
      "action": "add-include",
      "at": "2026-07-07T19:17:32.800783Z",
      "pattern": "src/scistudio/api/app.py",
      "reason": "Owner clarified Slack sending behavior must be cancelled, not just public Slack links."
    },
    {
      "action": "add-include",
      "at": "2026-07-07T19:17:32.800785Z",
      "pattern": "src/scistudio/telemetry/**",
      "reason": "Owner clarified Slack sending behavior must be cancelled, not just public Slack links."
    },
    {
      "action": "add-include",
      "at": "2026-07-07T19:17:32.800786Z",
      "pattern": "tests/packaging/test_no_alpha_gate.py",
      "reason": "Owner clarified Slack sending behavior must be cancelled, not just public Slack links."
    }
  ],
  "session_id": "8b2bff94-410f-42c0-8031-99e60e8a783e",
  "strictness_tier": 2,
  "task_kind": "guided",
  "test_events": [
    {
      "at": "2026-07-07T19:13:56.235495Z",
      "class": null,
      "kind": "path",
      "path": "tests/packaging/test_no_alpha_gate.py",
      "rationale": null,
      "verified_in_diff": null
    },
    {
      "at": "2026-07-07T19:17:32.800911Z",
      "class": null,
      "kind": "path",
      "path": "tests/packaging/test_no_alpha_gate.py",
      "rationale": null,
      "verified_in_diff": null
    }
  ]
}
